{"title": "從算力打到傳輸！這家卡位矽光子 法人點名下一個金礦", "summary": "", "link": "https://www.setn.com/News.aspx?NewsID=1794884", "published_my": "260214 010200", "site": "setn", "label": "setn"}
{"title": "「全世界最棒的地鐵」北捷5原因被加拿大歌手讚爆：24小時內被徹底征服", "summary": "", "link": "https://www.setn.com/News.aspx?NewsID=1795060", "published_my": "260214 010900", "site": "setn", "label": "setn"}
{"title": "川習會倒計時！台灣成最關鍵議題 陸學者：北京恐要求川普明確反對台獨", "summary": "", "link": "https://www.setn.com/News.aspx?NewsID=1795051", "published_my": "260214 011400", "site": "setn", "label": "setn"}
{"title": "外資／3天狂掃逾1300億！這3檔成吸金王 買超近30萬張", "summary": "", "link": "https://www.setn.com/News.aspx?NewsID=1794689", "published_my": "260214 011600", "site": "setn", "label": "setn"}
{"title": "網路上嘴秋！隨機殺人貼文下留「沒砍到賴清德真可惜」 台中男慘了", "summary": "", "link": "https://www.setn.com/News.aspx?NewsID=1795059", "published_my": "260214 012000", "site": "setn", "label": "setn"}
{"title": "蘇丹紅化粧品又增10家違規！ 韓製防曬精華、安瓶棒都中標", "summary": "", "link": "https://www.setn.com/News.aspx?NewsID=1795069", "published_my": "260214 012300", "site": "setn", "label": "setn"}
{"title": "原來挖冰淇淋有技巧？勺子要「先搖一搖」 Threads曝原因", "summary": "", "link": "https://www.setn.com/News.aspx?NewsID=1795063", "published_my": "260214 012700", "site": "setn", "label": "setn"}
{"title": "周杰倫直指「方文山變了」！ 合作27年突嘆：已經不是我認識的他", "summary": "", "link": "https://www.setn.com/News.aspx?NewsID=1795055", "published_my": "260214 013100", "site": "setn", "label": "setn"}
{"title": "三明治族調查曝光最怕這5種病 健康風險它一次扛！", "summary": "", "link": "https://www.setn.com/News.aspx?NewsID=1794715", "published_my": "260214 013300", "site": "setn", "label": "setn"}
{"title": "日圓創15個月來最大單週漲幅 高市早苗勝選穩定市場信心", "summary": "", "link": "https://www.setn.com/News.aspx?NewsID=1795056", "published_my": "260214 013400", "site": "setn", "label": "setn"}
{"title": "川普關稅由外國買單？2報告揭：全轉嫁給美國企業及消費者", "summary": "", "link": "https://www.setn.com/News.aspx?NewsID=1795054", "published_my": "260214 013700", "site": "setn", "label": "setn"}
{"title": "抗議烏俄戰爭！戴「紀念隊友頭盔」遭取消資格 烏選手：比奪牌有意義", "summary": "", "link": "https://www.setn.com/News.aspx?NewsID=1795049", "published_my": "260214 014100", "site": "setn", "label": "setn"}
{"title": "過年後診間湧現「看病潮」？ 爽吃一週驚見脂肪肝上身", "summary": "", "link": "https://www.setn.com/News.aspx?NewsID=1795071", "published_my": "260214 014500", "site": "setn", "label": "setn"}
{"title": "川普關稅陰影消退！美媒：貿易戰1年後「中國工廠港口仍燈火通明」", "summary": "", "link": "https://www.setn.com/News.aspx?NewsID=1795050", "published_my": "260214 014800", "site": "setn", "label": "setn"}
{"title": "大掃除廢電池、充電線別亂丟 正確回收方式一次看！做錯最慘罰6千", "summary": "", "link": "https://www.setn.com/News.aspx?NewsID=1795070", "published_my": "260214 015100", "site": "setn", "label": "setn"}
{"title": "美核發許可　英國石油等五大油商恢復在委內瑞拉營運", "summary": "美國當局今天核發許可，允許五家國際大型石油公司在委內瑞拉營運。川普政府抓捕委國總統馬杜洛（Nicolas Maduro）後，現正著眼於提升石油產量。\n\n法新社報導，美國財政部外國資產管制辦公...…", "link": "https://ec.ltn.com.tw/article/breakingnews/5343135", "published_my": "260214 015403", "site": "ltn", "label": "即時"}