{"title": "朱政騏涉共諜案遭綠開除！國安局認「有違法相關事證」：已進入司法程序", "summary": "", "link": "https://www.setn.com/News.aspx?NewsID=1819340", "published_my": "260408 100000", "site": "setn", "label": "setn"}
{"title": "汪浩時間》國共合作 消滅中華民國？", "summary": "2026年4月7日，鄭麗文率領規模空前的國民黨訪問團訪中。這場名為「和平」的旅行，實則是一場極不對稱的政治獻祭。這場交往並非互惠，而是向世界展示：台灣最大在野黨願意在中共設定的「一中框架...…", "link": "https://talk.ltn.com.tw/article/breakingnews/5396241", "published_my": "260408 100000", "site": "ltn", "label": "言論"}
{"title": "隨媽祖同行15載！正光製藥「聯合義診義賣」4/18起跑：傳遞愛心", "summary": "", "link": "https://www.setn.com/News.aspx?NewsID=1819052", "published_my": "260408 100000", "site": "setn", "label": "setn"}
{"title": "64公里外偵測F-15E飛官心跳！疑CIA秘密武器首度實戰立功", "summary": "美國總統川普6日在白宮舉行記者會，公開美軍營救F-15E飛官的部分任務細節，在記者會中，中央情報局長（CIA）雷克里夫（John Ratcliffe）表示，CIA使用尖端技術定位...…", "link": "https://news.ltn.com.tw/news/world/breakingnews/5396525", "published_my": "260408 100014", "site": "ltn", "label": "國際"}
{"title": "呼應58年前「地出」經典照！ 阿提米絲2號拍下震撼「地落」畫面", "summary": "美國航太總署（NASA）的「阿提米絲2號」（Artemis II）在台灣時間7日清晨1點56分左右，創下人類距離地球最遠太空飛行紀錄，太空人團隊在繞行到月背後，拍下「地落」（Ea...…", "link": "https://news.ltn.com.tw/news/world/breakingnews/5396528", "published_my": "260408 100046", "site": "ltn", "label": "國際"}
{"title": "峮峮被爆密戀小15歲李秉諭！經紀人回應緋聞", "summary": "中信兄弟啦啦隊女神峮峮（吳函峮），最近被週刊拍到和男團AcQUA源少年成員李秉諭(小名：貢丸)互動密切，因此傳出姊弟戀。對此，雙方經紀人表示，峮峮、李秉諭是前後輩的朋友關係。根據《時報周刊CTWANT", "link": "https://www.chinatimes.com/realtimenews/20260408001409-260404", "published_my": "260408 100100", "site": "chinatimes", "label": "chinatimes"}
{"title": "引誘開鏡頭「裸聊」！女網友嚇傻秒拒絕 男大生未得逞1原因判刑1年", "summary": "", "link": "https://www.setn.com/News.aspx?NewsID=1819307", "published_my": "260408 100100", "site": "setn", "label": "setn"}
{"title": "酸賴「面對大陸跟美國有雙標」 游淑慧：不是靠罵在野黨就可締造和平", "summary": "國民黨主席鄭麗文昨（7）日啟程展開「2026和平之旅」訪問中國大陸，同日總統賴清德上午也出席鄭南榕追思紀念會，並強調對和平要有理想不能有幻想，和平必須要看實力與爭取民主一樣，必須要有決心，靠實力才能得", "link": "https://www.chinatimes.com/realtimenews/20260408001466-260407", "published_my": "260408 100100", "site": "chinatimes", "label": "chinatimes"}
{"title": "TVB爆掌控藝人社交網  傳4藝人拒交帳號密碼", "summary": "〔娛樂頻道／綜合報導〕香港最新一期《東周刊》獨家爆料TVB為嚴管旗下藝人的社交網路，進而推出激進「辣招」，強制旗下藝人將IG、臉書、小紅書等社交平台的帳號密碼交由公司「中央管轄」，但有4藝人群起...…", "link": "https://ent.ltn.com.tw/news/breakingnews/5396532", "published_my": "260408 100150", "site": "ltn", "label": "影視"}
{"title": "民進黨高雄市議員參選人看板遭挖眼毀容 涉案男落網這樣說", "summary": "民進黨籍高雄市議員參選人鄧巧佩昨天報警，指她設在前鎮區公車站牌的廣告看板，遭人惡意毀損。警方追查後，查獲49歲顏姓男子涉案，初步了解，顏男稱是等候公車時，臨時起意以隨身攜帶鑰匙刮損看板。全案依違反公職", "link": "https://www.chinatimes.com/realtimenews/20260408001479-260402", "published_my": "260408 100200", "site": "chinatimes", "label": "chinatimes"}
{"title": "辜仲諒砸百億躍升最大股東　 台泥：歡迎認同公司長期策略的投資人", "summary": null, "link": "https://www.mirrormedia.mg/story/20260408fin001", "published_my": "260408 100200", "site": "mirrormedia", "label": "鏡傳媒"}
{"title": "辜仲諒砸101億元買進台泥5.26％ 躍為台泥第一大股東", "summary": "台泥 （1101） 今 （8） 日公告，中信慈善基金會董事長辜仲諒以自有資金約81.56億元及貸款20.1億元，共斥資101.66 億元取得台泥股份，每股買進均價約25....…", "link": "https://ec.ltn.com.tw/article/breakingnews/5396592", "published_my": "260408 100304", "site": "ltn", "label": "財經"}
{"title": "支持在地團體實踐永續好點子 太魯閣補助資源加碼！", "summary": "內政部國家公園署太魯閣國家公園管理處修正發布「夥伴共榮方案補捐助作業規範」，針對具發展潛力的計畫，如淨零碳排、社區環境改善或生態旅遊推動，補助上限由5萬元提升至15萬元，太管處...…", "link": "https://news.ltn.com.tw/news/life/breakingnews/5396567", "published_my": "260408 100329", "site": "ltn", "label": "生活"}
{"title": "士林分署123拍賣會吸引80人搶標！ 淡水捷運宅1032萬元拍定", "summary": "法務部行政執行署士林分署於昨（7）日下午舉辦「123聯合拍賣會」，儘管春雨綿綿，現場買氣依舊熱絡，吸引逾80名民眾及台北市立南湖高中師生踴躍參與。本次拍賣成果豐碩，其中位於新北...…", "link": "https://news.ltn.com.tw/news/society/breakingnews/5396562", "published_my": "260408 100333", "site": "ltn", "label": "社會"}
{"title": "嫌帕金森氏症老婦太吵「呼巴掌」  看護打完人後嚷著「不幹了」", "summary": "越南籍阮姓看護受雇照護罹患帕金森氏症、幾無自理能力的徐姓老婦，疑因不耐老婦頻繁呼喚，趁家屬暫離病房之際，狠心掌摑老婦右臉。阮婦打完人嚷著離職，徐婦趁機呼救，家屬氣炸爆警，阮婦被...…", "link": "https://news.ltn.com.tw/news/society/breakingnews/5396589", "published_my": "260408 100339", "site": "ltn", "label": "社會"}
{"title": "T.O.P回歸放大絕！聯手《魷魚遊戲》團隊拍MV超狂", "summary": "南韓天團BIGBANG前成員「T.O.P」崔勝炫近來帶著首張個人正規專輯強勢回歸，第二波主打《完全瘋了！（Studio54）》還沒正式公開，就先靠「陣容」掀起熱議。\n\n\n\n\n\n...…", "link": "https://ent.ltn.com.tw/news/breakingnews/5396590", "published_my": "260408 100403", "site": "ltn", "label": "影視"}
{"title": "鄭麗文訪中重申九二共識 陳培瑜批拋棄捍衛台灣立場", "summary": "國民黨主席鄭麗文7日率團訪問中國，晚間於南京東郊國賓館「和平廳」接受中共中央台辦主任宋濤的晚宴。鄭麗文致詞時強調此次出訪的四大意義，也再次證明「九二共識、反對台獨」的政治基礎仍「...…", "link": "https://news.ltn.com.tw/news/politics/breakingnews/5396448", "published_my": "260408 100443", "site": "ltn", "label": "政治"}
{"title": "伊朗開放荷姆茲2周！黃金大回血飆漲逾3％ 專家看好下一步驚喜價", "summary": "美伊緊張局勢於 7 日迎來轉折，雙方達成暫停火2週的協議，帶動市場避險情緒回穩。受此激勵國際金價單日飆漲逾 3%，盤中一度重返每盎司4850美元 大關。瑞銀（UBS）分析指出，儘管金價短期內仍可能面臨", "link": "https://www.chinatimes.com/realtimenews/20260408001504-260410", "published_my": "260408 100500", "site": "chinatimes", "label": "chinatimes"}
{"title": "鐵件掉落車道釀禍 國1林口路段12車輾過車體受損", "summary": "國道1號南向43.7公里林口路段，今（8）日凌晨1點多發生鐵件掉落，後方車輛閃避不及輾過，高達12輛車的車體毀損；國道公路警察局第一公路警察大隊表示，陸續接獲車主報案，正擴大調...…", "link": "https://news.ltn.com.tw/news/society/breakingnews/5396576", "published_my": "260408 100515", "site": "ltn", "label": "社會"}
{"title": "高雄男精神不濟連撞對向3車 撞斷路燈波及店家玻璃", "summary": "高雄市三民區天祥一路今（8）日上午5時45分許發生交通事故，尤姓男駕駛（21歲）駕駛轎車，西向東方向直行於天祥一路上，疑因精神不濟，竟行駛至對向車道，追撞停於對向路旁停車格的2...…", "link": "https://news.ltn.com.tw/news/society/breakingnews/5396597", "published_my": "260408 100540", "site": "ltn", "label": "社會"}
{"title": "【弘光盃大專校院跆拳道錦標賽】陸專跆拳道隊踢下4金2銅 展拚戰精神", "summary": "陸軍專科學校跆拳道隊日前參加「第19屆弘光盃全國大專校院跆拳道錦標賽」，憑藉卓越實力，勇奪4金2銅佳績，不僅奪下男子團體冠軍，更以優異成績與團體拚戰精神，榮膺賽事最高榮譽「精神總錦標」，充分展現平時", "link": "https://www.chinatimes.com/realtimenews/20260408000071-260417", "published_my": "260408 100600", "site": "chinatimes", "label": "chinatimes"}
{"title": "焦點股》旺宏：營收激增 跳空漲停", "summary": "記憶體廠旺宏（2337）昨公佈自結3月份合併營收為新台幣44.22億元，月增加45.9%，年增加96.5%，創51個月新高。營收利多激勵，今股價跳空漲停至150元鎖住，一...…", "link": "https://ec.ltn.com.tw/article/breakingnews/5396598", "published_my": "260408 100633", "site": "ltn", "label": "財經"}
{"title": "鄭麗文中山陵謁陵 中國民眾：歡迎來南京支持海峽兩岸和平統一", "summary": "國民黨主席鄭麗文訪中之行第二天到南京中山陵謁陵，向國民黨創黨總理孫中山致敬，吸引數百名民眾在外圍觀，其中一位中國民眾受訪表示，歡迎鄭麗文主席來南京，「支持海峽兩岸和平統一」。\n...…", "link": "https://news.ltn.com.tw/news/politics/breakingnews/5396557", "published_my": "260408 100648", "site": "ltn", "label": "政治"}
{"title": "鄭問藍綠為何不能和解 侯友宜：從事公職都要以民為念", "summary": "國民黨主席鄭麗文出訪大陸展開「和平之旅」前召開記者會，表示如果國共兩黨能夠和解，藍綠之間為什麼不能？對此新北市長侯友宜今（8）日表示，我們所有的政策以及考量都要以人民的福利為最大的一個方向。侯友宜強調", "link": "https://www.chinatimes.com/realtimenews/20260408001497-260407", "published_my": "260408 100700", "site": "chinatimes", "label": "chinatimes"}
{"title": "連假醫院休息！天母秋田犬咬死紅貴賓 飼主眼見愛犬在懷中斷氣", "summary": "", "link": "https://www.setn.com/News.aspx?NewsID=1819350", "published_my": "260408 100800", "site": "setn", "label": "setn"}
{"title": "鄭麗文稱九二共識歷久彌新？葉耀元3點戳破：沒共識、想侵台", "summary": "國民黨主席鄭麗文7日率團赴中訪問，中國國台辦主任宋濤在上海虹橋機場為鄭一行人接機。鄭麗文強調，此次訪問再次證明「九二共識、反對台獨」政治基礎，仍然歷久彌新，仍是當前兩岸關係的定海...…", "link": "https://news.ltn.com.tw/news/politics/breakingnews/5396536", "published_my": "260408 100800", "site": "ltn", "label": "政治"}
{"title": "新店疑食物中毒案3分店暫停營業 侯友宜：等待檢驗結果該罰就罰", "summary": "清明連假期間，新北市新店區便當店「清六食堂」疑似爆發食物中毒案，截至昨天下午，通報人數已有44人，目前清六食堂3家分店（公所店、中興店及民權店）都暫停營業。新北市長侯友宜今天表...…", "link": "https://news.ltn.com.tw/news/life/breakingnews/5396579", "published_my": "260408 100837", "site": "ltn", "label": "生活"}
{"title": "《化工股》庫存調整ing 材料*-KY首季營收年減35%", "summary": "產業仍處於庫存調整階段，材料*-KY(4763)3月合併營收9.77億元、月增30%、年減36%，首季合併營收為27.11億元、年減35%。  材料-KY指出，目前近期產業仍處於庫存調整階段，部分客戶", "link": "https://www.chinatimes.com/realtimenews/20260408001550-260410", "published_my": "260408 100900", "site": "chinatimes", "label": "chinatimes"}
{"title": "《通網股》矽光子需求噴發 聯亞衝高、外資潑冷水維持賣出", "summary": "日系外資出具最新研究報告指出，聯亞（3081）公布2026年第一季營收表現明顯優於市場預期，主要受惠於矽光子（SiPh）需求快速升溫，背後動能來自雲端服務供應商（CSP）積極擴建AI資料中心。不過，儘", "link": "https://www.chinatimes.com/realtimenews/20260408001545-260410", "published_my": "260408 100900", "site": "chinatimes", "label": "chinatimes"}
{"title": "黃明志持毒案再開庭！現身天后宮「媽祖給這指示」親揭官司進度", "summary": "", "link": "https://www.setn.com/News.aspx?NewsID=1819352", "published_my": "260408 100900", "site": "setn", "label": "setn"}
{"title": "《基金》主動式台股ETF受益人連24週創高 這幾檔人氣續旺", "summary": "主動式台股ETF魅力持續發燒，根據集保戶股權分散至4月2日最新統計資料，12檔主動式台股ETF受益人數上周增加4.6萬人，總人數來到108萬7225人已連續24週創新高。統計今年來已增加超過60萬人來", "link": "https://www.chinatimes.com/realtimenews/20260408001549-260410", "published_my": "260408 100900", "site": "chinatimes", "label": "chinatimes"}
{"title": "《半導體》創見營收倍增 月季同登高", "summary": "創見(2451)公布2026年3月份及第一季合併營收數據。今年3月單月營收為新台幣56.83億元，年增380.57%、月增78.49%，再度創下歷史單月新高；累計第一季合併營收達新台幣136.28億元", "link": "https://www.chinatimes.com/realtimenews/20260408001548-260410", "published_my": "260408 100900", "site": "chinatimes", "label": "chinatimes"}
{"title": "輾壓星巴克！印尼咖啡霸主全台首店來了 狂賣10萬杯拿鐵、開心果瑪奇朵", "summary": "", "link": "https://www.setn.com/News.aspx?NewsID=1819351", "published_my": "260408 100900", "site": "setn", "label": "setn"}
{"title": "美伊交戰陸淡定 陸學者：對北京影響「反而是正面」", "summary": "美國與以色列對伊朗發動攻擊已逾1個月，美國總統川普（Donald Trump）與伊朗高層於台灣時間8日清晨相繼宣布接受停火2周。面對戰火嚴重影響全球能源供應，北京清華大學經濟管理學院教授曹遠征認為，對", "link": "https://www.chinatimes.com/realtimenews/20260408001474-260409", "published_my": "260408 100900", "site": "chinatimes", "label": "chinatimes"}
{"title": "燕鷗進入繁殖季 澎湖縣政府推動生態友善旅遊", "summary": "每年4至9月為燕鷗繁殖期，燕鷗屬國家公告第二級保育類野生動物（珍貴稀有物種），對外界干擾極為敏感，呼籲民眾與遊客共同守護其棲地安全，避免不當行為影響其繁殖，尤其部分業者以餵食燕...…", "link": "https://news.ltn.com.tw/news/life/breakingnews/5396603", "published_my": "260408 100901", "site": "ltn", "label": "生活"}
{"title": "評伊朗10點和平方案「練肖話」 專家曝美軍盤算：這次停戰只是中場休息", "summary": "", "link": "https://www.setn.com/News.aspx?NewsID=1819356", "published_my": "260408 101000", "site": "setn", "label": "setn"}
{"title": "假借撿手機摸外籍女看護下體 中古車行色老闆二審獲緩刑", "summary": "基隆市中古車行陳姓老闆見外籍女看護小敏（化名）年幼可欺，假借手機掉進店內1輛中古車駕駛座內，騙小敏幫他撿手機時，趁機摸小敏的臀部與下體。基隆地院去年11月審結，依強制猥褻罪判陳...…", "link": "https://news.ltn.com.tw/news/society/breakingnews/5396591", "published_my": "260408 101035", "site": "ltn", "label": "社會"}
{"title": "王惠美遞計畫書遭李洋6字打槍 林楚茵：趕快打電話藍委放行預算", "summary": "超尷尬！彰化縣和美全民運動館7日舉行啟用典禮，運動部長李洋也到場參加，彰化縣長王惠美見機不可失，馬上拿出一包牛皮紙袋要給李洋，強調裡頭有彰化縣還需要建設的4座全民館計畫書費，但李...…", "link": "https://news.ltn.com.tw/news/politics/breakingnews/5396494", "published_my": "260408 101053", "site": "ltn", "label": "政治"}
{"title": "暫時停火仍存風險？FBI警告伊朗持續威脅美國", "summary": "雖美國總統川普表示，已與伊朗達成為期2週的停火協議。但《路透》審閱的執法情報報告顯示，聯邦調查局（FBI）上個月才向美國州和地方執法部門發出警告，稱伊朗政府對美國境內目標構成日...…", "link": "https://news.ltn.com.tw/news/world/breakingnews/5396534", "published_my": "260408 101057", "site": "ltn", "label": "國際"}
{"title": "春雨為德基水庫進帳近2000公噸   台中市水情會取消綠燈改正常？", "summary": "這波春雨為德基水庫帶來近2000萬噸的進水量，目前水庫水位已達1390.07公尺，蓄水量12014.9萬噸，蓄水率65.18%，較4月3日之前蓄水率上升10%以上，台中市水情是...…", "link": "https://news.ltn.com.tw/news/life/breakingnews/5396569", "published_my": "260408 101120", "site": "ltn", "label": "生活"}
{"title": "不只女生！他赴日遭時髦男「熱情搭訕」嚇傻 內行揭恐怖目的", "summary": "", "link": "https://www.setn.com/News.aspx?NewsID=1819354", "published_my": "260408 101200", "site": "setn", "label": "setn"}
{"title": "郭書瑤低胸失守直接端上桌！北半球太搶戲 全網直接失守", "summary": "", "link": "https://www.setn.com/News.aspx?NewsID=1819347", "published_my": "260408 101200", "site": "setn", "label": "setn"}
{"title": "罷免川普！鐵粉也翻臉 跨黨派要引用美憲法第25修正案", "summary": "從加徵關稅，到和以色列聯手，重拳攻打伊朗，美國總統川普不斷出招，撼動全球，再度激起跨黨派引用憲法第25條修正案的聲浪。近年來美國國會議員一再提出憲法規定的罷免總統法，而2021年1月6日國會大廈攻擊事", "link": "https://www.chinatimes.com/realtimenews/20260408001420-260408", "published_my": "260408 101200", "site": "chinatimes", "label": "chinatimes"}
{"title": "中共劃5空域保留區！國安局曝目的：「川習會」前試探美國空域活動狀況", "summary": "", "link": "https://www.setn.com/News.aspx?NewsID=1819355", "published_my": "260408 101200", "site": "setn", "label": "setn"}
{"title": "桃客三峽站傳職場霸凌、性平事件 桃客：性平會已調查完畢", "summary": "讀者向本報爆料指出，桃園客運三峽站內部發生職場霸凌與不當管理問題，公車女司機（簡稱Z女）誹謗一位懷孕女司機，還霸凌一位透過政府受訓既就業（MOU）方案進入職場的65歲司機，三峽...…", "link": "https://news.ltn.com.tw/news/life/breakingnews/5396588", "published_my": "260408 101226", "site": "ltn", "label": "生活"}
{"title": "懲處李貞秀延後 黃帝穎：不敢開除恐坐實中共指派", "summary": "民眾黨不分區立委李貞秀爭議不斷，除了雙重國籍仍存疑義，她日前在直播上放話也引發黨內不滿，儘管李貞秀已遭檢舉送中評會，原定9日開會討論懲處，但傳出中評會已延期到13日舉行。對此律師...…", "link": "https://news.ltn.com.tw/news/politics/breakingnews/5396596", "published_my": "260408 101252", "site": "ltn", "label": "政治"}
{"title": "現金愈來愈不值錢？通膨時代下的資產配置轉向　看懂房地產的保值新邏輯", "summary": null, "link": "https://www.mirrormedia.mg/story/20260408edi013", "published_my": "260408 101300", "site": "mirrormedia", "label": "鏡傳媒"}
{"title": "美伊各自宣布大獲全勝！伊朗持續與以色列互轟　海灣國家仍被波及", "summary": "<br />\n<br />\nNewtalk新聞 <br />\n<br />\n<p>美國與伊朗稍早雙雙宣布達成停火兩周的共識，伊朗宣稱取得重大勝利，美國總統川普也提到是由他同意暫停對伊朗轟炸，已完成所有軍事目標。不過，伊朗和以色列之間的戰鬥並未停止，雙方仍在互相轟炸。</p><br />\n<p>川普在 Truth Social 發文表示「根據我與巴基斯坦總理夏立夫（Shehbaz Sharif），以及巴基斯坦陸軍元帥穆尼爾的談話內容，他們請求我暫緩今晚即將對伊朗動用的破壞性軍事力量；在此同時，前提是伊朗伊斯蘭共和國同意完全、立即且安全地開放荷姆茲海峽，我同意暫停對伊朗的轟炸與攻擊行動，為期兩週。這將是一項雙方共同遵守的停火協議！」</p><br />\n<p>川普表示，「這麼做的原因在於，我們已經達成並超越所有軍事目標，且在推動與伊朗達成關於長期和平，以及中東地區和平的明確協議方面，已經取得非常顯著的進展。」</p><br />\n<p>伊朗最高國家安全委員會（Supreme National Security Council）發布的聲明，伊朗表示已取得重大勝利，並迫使美國接受伊朗的10點方案。聲稱美國已經全面接受伊朗提出的「十點和平計畫」（10-point peace plan），內容極具指標性，包括美方保證不再攻擊伊朗、承認伊朗對荷莫茲海峽的控制權。伊朗外交部長阿拉格奇更提到，若美國確定停火，伊朗將在兩周後開放荷姆茲海峽。</p><br />\n<p>然而，在美伊停火後，伊朗和以色列之間似乎仍未鬆手，以色列時報提到，伊朗最近一次向以色列南部發射彈道飛彈攻擊後，兩名青少年在特爾謝瓦受輕傷，且伊朗持續對海灣國家發動攻擊。</p><br />\n<p>根據美聯社報導，以色列軍方官員稱，在白宮表示以色列已同意停火後，以色列仍在對伊朗發動攻擊。</p><p><p>延伸閱讀：</p></p><p><p><a href=\"https://newtalk.tw/news/view/2026-04-06/1028271\" target=\"_blank\">美媒：中間人斡旋美伊談判「45天停火協議」　盼分兩階段永久停戰</a></p></p><p><p><a href=\"https://newtalk.tw/news/view/2026-04-08/1028587\" target=\"_blank\">中國能源凍未條？美媒：中國官員鼓勵伊朗與美停火</a></p></p><p><p><a href=\"https://newtalk.tw/news/view/2026-04-07/1028398\" target=\"_blank\">伊提10點回應! 要求「永久停火」、「解除制裁」 以憂談判失敗持續狂轟</a></p></p><p><p><a href=\"https://newtalk.tw/news/view/2026-04-06/1028219\" target=\"_blank\">伊朗年初血腥鎮壓濫殺平民！川普：美國之後曾向抗議者送大量槍支</a></p></p><p><p><a href=\"https://newtalk.tw/news/view/2026-04-07/1028433\" target=\"_blank\">曾命中台積電800元以下是好買點 謝金河看今年伊朗戰爭「川普三部曲」</a></p></p>", "link": "https://newtalk.tw/news/view/2026-04-08/1028595", "published_my": "260408 101300", "site": "newtalk", "label": "全部"}
{"title": "伊朗宣稱取得重大勝利「迫使」美接受10點方案! 要求撤軍解除制裁", "summary": "<br />\n<br />\nNewtalk新聞 <br />\n<br />\n<p>美國和伊朗的戰爭出現轉折，伊朗最高國家安全委員會（Supreme National Security Council）今（8）天發布聲明宣告，伊朗在本次戰爭中幾乎已實現所有目標，取得重大勝利。敵人遭遇了「歷史性且徹底的失敗」，伊朗將透過談判鞏固勝利成果。在最高領袖的建議與委員會批准下決定接受由巴基斯坦提出的停火提議，並迫使美國接受伊朗的10點方案。</p><br />\n<p>根據美國有線電視新聞網（CNN）及英國廣播公司（BBC）、華爾街日報報導，伊朗最高國家安全委員會表示，目前伊朗已取得偉大成果，並將致力於在地區內建立新的安全與政治格局。為了確定停火細節，雙方決定在伊斯蘭堡舉行談判。伊朗已拒絕敵方提出的所有計畫，並另外制定一項「10點計畫」，目前已透過巴基斯坦提交給美國方面。</p><br />\n<p>伊朗最高國家安全委員會指出，作為10點方案的一部分，美國原則上同意解除針對伊朗的所有主要與次要制裁。美國同意接受伊朗的核濃縮活動，並承認伊朗對關鍵能源通道荷姆茲海峽（Strait of Hormuz）的持續控制。伊朗最高國家安全委員宣稱：「敵人在對伊朗人民發動的不公、非法且犯罪的戰爭中，遭受了無可否認、歷史性且毀滅性的失敗。」</p><br />\n<p>伊朗方面強調，這份計畫所達成的所有協議，未來將成為具有約束力的國際法。伊朗委員會認為，這將為伊朗民族帶來一場極具意義的外交勝利。此外，伊朗國營媒體也報導美國總統川普（Donald Trump）的社群媒體貼文，標題指稱：「川普宣布停火兩週，接受伊朗結束戰爭的條件」，並形容這是「川普在反伊朗言論上的屈辱性退讓」。</p><br />\n<p>巴基斯坦在美國與以色列對伊朗的衝突中擔任斡旋者角色，川普也在自家社群平台「真實社群」（Truth Social）發文透露，巴基斯坦總理夏立夫（Shehbaz Sharif）是與他討論、促成這次有條件停火協議的人士之一。貼文中也提到巴基斯坦陸軍參謀長穆尼爾（Asim Munir）。川普聲稱，他們「請求我暫緩今晚即將對伊朗發動的毀滅性武力」。</p><br />\n<p>伊朗國家最高安全委員會轄下「努爾新聞」（Nour News）所公布的清單內容如下：</p><br />\n<p>1. 美國必須根本性地承諾保證不進行侵略。</p><br />\n<p>2. 伊朗持續掌控荷姆茲海峽。</p><br />\n<p>3. 接受伊朗可為其核計畫進行鈾濃縮。</p><br />\n<p>4. 解除對伊朗的所有首要制裁。</p><br />\n<p>5. 解除針對與伊朗機構往來的外國實體的所有次級制裁。</p><br />\n<p>6. 終結所有聯合國安理會針對伊朗的決議。</p><br />\n<p>7. 終止所有國際原子能總署（IAEA）關於伊朗核計畫的決議。</p><br />\n<p>8. 支付伊朗因戰爭所受損失的賠償金。</p><br />\n<p>9. 美國戰鬥部隊撤離中東地區。</p><br />\n<p>10. 各戰線全面停火，包括以色列與黎巴嫩武裝組織真主黨（Hezbollah）的衝突。</p><p><p>延伸閱讀：</p></p><p><p><a href=\"https://newtalk.tw/news/view/2026-04-06/1028219\" target=\"_blank\">伊朗年初血腥鎮壓濫殺平民！川普：美國之後曾向抗議者送大量槍支</a></p></p><p><p><a href=\"https://newtalk.tw/news/view/2026-04-06/1028271\" target=\"_blank\">美媒：中間人斡旋美伊談判「45天停火協議」　盼分兩階段永久停戰</a></p></p><p><p><a href=\"https://newtalk.tw/news/view/2026-04-07/1028398\" target=\"_blank\">伊提10點回應! 要求「永久停火」、「解除制裁」 以憂談判失敗持續狂轟</a></p></p><p><p><a href=\"https://newtalk.tw/news/view/2026-04-08/1028587\" target=\"_blank\">中國能源凍未條？美媒：中國官員鼓勵伊朗與美停火</a></p></p><p><p><a href=\"https://newtalk.tw/news/view/2026-04-07/1028452\" target=\"_blank\">既然贏了就該收錢! 川普震撼提議 : 非伊朗 美國才該徵收核姆茲通行費</a></p></p>", "link": "https://newtalk.tw/news/view/2026-04-08/1028579", "published_my": "260408 101334", "site": "newtalk", "label": "全部"}
{"title": "台中雨炸成災！北區路樹突倒塌壓車 橫躺道路驚險畫面曝", "summary": "台中市今天清晨大雨未歇，北區南京東路一帶突傳出巨響，一棵路樹疑不敵連日豪雨侵襲，應聲倒塌橫躺路面，粗壯枝幹重壓路旁停放車輛，現場枝葉四散、路面濕滑凌亂，所幸未造成人員傷亡。\n...…", "link": "https://news.ltn.com.tw/news/life/breakingnews/5396587", "published_my": "260408 101346", "site": "ltn", "label": "生活"}
{"title": "曾敬驊秘戀美妝網紅羅念！雙方被爆「2年前就搭上｣ 大姐也按讚應援", "summary": "", "link": "https://www.setn.com/News.aspx?NewsID=1819358", "published_my": "260408 101400", "site": "setn", "label": "setn"}
{"title": "鄭麗文訪中傷選情？ 牛煦庭：開大門走大路才能揮別PTSD", "summary": "<br />\n<br />\nNewtalk新聞 <br />\n<br />\n<p>國民黨主席鄭麗文昨以「和平之旅」名義率團訪中，遭綠營諷刺為「躺平投降之旅」。對此，國民黨發言人立委牛煦庭今（8日）接受中廣節目《千秋萬事》專訪期間，他表示，國民黨在兩岸議題被抹紅，甚至輸掉選舉，但如果畏畏縮縮什麼都不做，還是會被貼標籤，乾脆開大門走大路，才能揮別PTSD（創傷後壓力症候群）陰影。</p><br />\n<p>牛煦庭表示，獨裁者很有可能瞬間毀壞和平，所以要控管風險，如果當總統連風險控管的概念都沒有，他們真的非常懷疑總統的能力。獨裁者確實存在，而且可以用單邊的力量改變很多事情，身為一國的總統，應該理解現實才能解決問題，搞政治不就是為了解決問題嗎？獨裁者破壞和平的時候，你的方法是什麼？這才是大家要問的問題。</p><br />\n<p>牛煦庭強調，對話就是為了降低風險、避免衝突，這是方法之一，而且可以用，「你為什麼不用，因為你要搞選舉，因為你要搞意識形態。民進黨從總統到官員就是這個水準，大家怎麼會覺得把台灣的未來交在這群人手上會安全呢？」。他質問，民進黨滿口「抗中保台」，可是真正的作為是什麼？政黨到處都是共諜，這叫事實。</p><br />\n<p>牛煦庭強調，國民黨一直以來都主張兩岸可以透過對話的方式，來控管風險降低衝突的可能性 ，可以透過對話讓大家不要戰爭，讓局勢可以穩定，讓風險可以控管，哪一個政黨去又有什麼不好的？</p><br />\n<p>對於美方頻頻關切軍購案遲遲未通過。牛煦庭表示，美國人可以不管台灣的內政，但是中華民國的立法委員不能不管台灣的內政，他們服務的是中華民國國民，他們不服務外國人，所以要在這個過程之中去取得平衡，這才是重要的。</p><br />\n<p>牛煦庭表示，強化國防速度才是關鍵，民進黨堅持1.25兆元的軍購一毛不讓，但什麼時候才會建立完成，朝野僵局也是審預算很慢的原因，要問問民進黨政府，整個過程做了哪些努力？還是從頭到尾就是要操作政治？這是台灣社會要一起面對的。</p><br />\n<p>至於總預算僵局。牛煦庭表示，「賴皮政府」已經不是一天兩天了，反正在野黨通過了，執政黨就是不會埋買，也不執行幫軍人加薪，大家在連續的對抗裡面已經陷入麻痹，作為一個立法委員 ，非常希望大家拿出智慧來解決僵局。</p><p><p>延伸閱讀：</p></p><p><p><a href=\"https://newtalk.tw/news/view/2026-04-08/1028603\" target=\"_blank\">繞過修憲下修18歲選舉權？ 綠委曝主因：修法為取得釋憲門票</a></p></p><p><p><a href=\"https://newtalk.tw/news/view/2026-04-08/1028593\" target=\"_blank\">鄭麗文赴中同日！共機2架次逾越中線 海空兵力持續擾台 </a></p></p><p><p><a href=\"https://newtalk.tw/news/view/2026-04-07/1028420\" target=\"_blank\">訪中帶上「九二共識」創始人  鄭麗文再喊話賴清德和解 </a></p></p><p><p><a href=\"https://newtalk.tw/news/view/2026-04-07/1028506\" target=\"_blank\">鄭麗文飛抵上海獲禮遇 宋濤：奉習近平指示來迎接 </a></p></p><p><p><a href=\"https://newtalk.tw/news/view/2026-04-07/1028370\" target=\"_blank\">鄭麗文今訪中　管碧玲：「連胡會」換WHO「中國台灣省」是糖衣毒藥</a></p></p>", "link": "https://newtalk.tw/news/view/2026-04-08/1028609", "published_my": "260408 101429", "site": "newtalk", "label": "全部"}
{"title": "美伊才宣布停火 飛彈襲以色列、波灣多國 空襲警報大響", "summary": "美國與伊朗相繼宣布停火2周後不久，以色列及巴林、阿拉伯聯合大公國、科威特等波灣多國仍響起防空警報，警告民眾有無人機及飛彈來襲。綜合路透、CNN、《以色列時報》等報導，台灣時間8日清晨，美國總統川普與伊", "link": "https://www.chinatimes.com/realtimenews/20260408001552-260408", "published_my": "260408 101500", "site": "chinatimes", "label": "chinatimes"}
{"title": "中石化將公布重大消息 4月8日起暫停交易", "summary": "", "link": "https://www.setn.com/News.aspx?NewsID=1819362", "published_my": "260408 101500", "site": "setn", "label": "setn"}
{"title": "王惠美爭場館預算遭拒 林楚茵：總預算沒過 李洋也變不出來", "summary": "彰化縣長王惠美爭取運動中心經費，因同黨立委不審總預算落空，民進黨發言人林楚茵今表示，國民黨一邊擋錢一邊要錢；總預算沒過，部長也變不出運動中心。王惠美當場向李洋遞交爭取其他運動中心經費的計畫書，沒想到李", "link": "https://www.chinatimes.com/realtimenews/20260408001562-260407", "published_my": "260408 101600", "site": "chinatimes", "label": "chinatimes"}
{"title": "彰化3宮廟新設自動回收機  寶特瓶、鋁罐、電池直接儲值變現", "summary": "為讓資源回收更方便，彰化縣環保局推動智慧化自動回收機設置，去年第一台機台上路就吸引大量民眾使用，單月回收量3萬件，寶特瓶占近7成最多，今年進一步把設置地點從公所延伸到宮廟，讓民...…", "link": "https://news.ltn.com.tw/news/life/breakingnews/5396606", "published_my": "260408 101622", "site": "ltn", "label": "生活"}
{"title": "AI伺服器需求超猛！台光電3月、Q1 營收雙創歷史新高", "summary": "CCL大廠台光電（2383）3月合併營收達120.1億元，月增17.83％、年增56.63％；第一季合併營收330.67億元，季增32.66％、年增52.49％，單月與單季同步改寫歷史新高。台光電表示", "link": "https://www.chinatimes.com/realtimenews/20260408001456-260410", "published_my": "260408 101700", "site": "chinatimes", "label": "chinatimes"}
{"title": "跑山獸收費尋遺體遭酸「賞金獵人」！搜救教官刪文後再發文「2度炎上」", "summary": "", "link": "https://www.setn.com/News.aspx?NewsID=1819315", "published_my": "260408 101700", "site": "setn", "label": "setn"}
{"title": "日職》1、2場先發都奪勝 郭俊麟就被學長提醒：「你會被情蒐得很徹底」", "summary": "在徐若熙日職初先發奪勝之前，郭俊麟是上一位在日職寫下同樣紀錄的台灣投手，他更在旅日生涯的第1、2場先發都奪勝，只是他也坦言：「第2場投贏之後，就有一些學長跟我講，可能會被...…", "link": "https://sports.ltn.com.tw/news/breakingnews/5396609", "published_my": "260408 101757", "site": "ltn", "label": "即時"}
{"title": "台燿高階CCL占比升溫 3月營收年增72.34％ 創高", "summary": "CCL廠台燿（6274）公告3月營收37.82億元，年增72.34％，刷新單月新高紀錄；累計第一季營收100.56億元，年增57.89％。該公司表示，成長主因來自產品組合優化。法人指出，台燿近年聚焦M", "link": "https://www.chinatimes.com/realtimenews/20260408001495-260410", "published_my": "260408 101800", "site": "chinatimes", "label": "chinatimes"}
{"title": "人事未定影響年底選舉？中選會：盼新任委員及早就任", "summary": "藍白上個月封殺民進黨政府推薦的中選會人選僅通過主委游盈隆及在野黨團所推薦人選，行政院迄今仍未啟動交接及就職等程序。立法院內政委員會今日審查「公職人員選舉罷免法修正草案」，國民黨...…", "link": "https://news.ltn.com.tw/news/politics/breakingnews/5396610", "published_my": "260408 101807", "site": "ltn", "label": "即時"}
{"title": "「Peter陳」炒股海削逾2億涉犯證交法 檢起訴求刑16年", "summary": "曾捲入和旺禿鷹等多起炒股案的股市炒手陳建霖（綽號Peter陳）10多年前被台北、台中地檢署通緝，卻冒用友人江國億的身分，於2015年至2019年間與友人李明遠、業務員吳...…", "link": "https://news.ltn.com.tw/news/society/breakingnews/5396608", "published_my": "260408 101852", "site": "ltn", "label": "即時"}
{"title": "《興櫃股》凱鈿點點簽整合行動自然人憑證 秒速完成數位簽章", "summary": "隨著數位發展部近年積極建構數位信任（Digital Trust）生態圈及《電子簽章法》修法後明確賦予數位簽章強大的法律推定效力，具備高強度驗證的身分識別已成為防範詐騙、建立安全契約的核心。凱鈿(773", "link": "https://www.chinatimes.com/realtimenews/20260408001592-260410", "published_my": "260408 101900", "site": "chinatimes", "label": "chinatimes"}
{"title": "每月多領2500元！「單身、婚育」租屋族都有份 台北幸福租今天上路", "summary": "", "link": "https://www.setn.com/News.aspx?NewsID=1819336", "published_my": "260408 101900", "site": "setn", "label": "setn"}
{"title": "《光電股》創為聯手友來新能源 助攻鈣鈦礦量產", "summary": "創為精密(6899)宣布與友來新能源達成戰略合作，正式切入鈣鈦礦太陽能產業鏈，創為精密也在本周登場的Touch Taiwan 2026展覽中，以「鈣鈦礦 x 環境 IoT：天生一對」為題，展示與友來新", "link": "https://www.chinatimes.com/realtimenews/20260408001594-260410", "published_my": "260408 101900", "site": "chinatimes", "label": "chinatimes"}
{"title": "《櫃買市場》澤聖擺渡4月10登錄創櫃板", "summary": "澤聖擺渡國際事業公司(7411)4月10日登錄創櫃板。  澤聖擺渡國際事業公司(以下簡稱澤聖擺渡公司；產業類別：其他)主要業務為經營寵物生命紀念園區，該公司係採用符合環保法規之火化設備及生物處理技術，", "link": "https://www.chinatimes.com/realtimenews/20260408001600-260410", "published_my": "260408 101900", "site": "chinatimes", "label": "chinatimes"}
{"title": "《國際政治》不甩川普停火 以伊再度互轟 波灣天然氣設施遇襲", "summary": "在美國總統川普宣布對伊朗停火兩周後，據以色列《 Channel 12》報導，以色列軍方在周三清晨對伊朗發動了新一波空襲。　報導指出，在伊朗繼續向以色列發射飛彈後，以色列對伊朗的飛彈發射設施發動新的軍事", "link": "https://www.chinatimes.com/realtimenews/20260408001597-260410", "published_my": "260408 101900", "site": "chinatimes", "label": "chinatimes"}
{"title": "笨賊拿西瓜刀搶劫計程車！運將「神操作」反鎖車門 警10分鐘火速逮人", "summary": "", "link": "https://www.setn.com/News.aspx?NewsID=1819363", "published_my": "260408 102000", "site": "setn", "label": "setn"}
{"title": "曾被點名參戰台北市長 林右昌宣布「重要決定」：將暫時離開台灣", "summary": "", "link": "https://www.setn.com/News.aspx?NewsID=1819360", "published_my": "260408 102000", "site": "setn", "label": "setn"}
{"title": "綠台北市長人選未定！粉專曝6人選「6種命運」：要讓誰承擔哪種命運？", "summary": "", "link": "https://www.setn.com/News.aspx?NewsID=1819343", "published_my": "260408 102100", "site": "setn", "label": "setn"}
{"title": "鄭麗文訪中稱和平之旅 侯友宜：堅守自由民主的方向永不變", "summary": "國民黨主席鄭麗文昨天（7日）起率團訪問中國，展開「2026和平之旅」，新北市長侯友宜今天表示，要以中華民國的利益為最大考量，堅守民主自由的方向，永遠不會變。\n\n侯友宜今天在...…", "link": "https://news.ltn.com.tw/news/politics/breakingnews/5396615", "published_my": "260408 102128", "site": "ltn", "label": "即時"}
{"title": "被爆逼藝人交出社交網站密碼   香港TVB發聲回應", "summary": "〔娛樂頻道／綜合報導〕香港娛樂圈驚爆電視台控管旗下藝人內幕，傳聞TVB為嚴管旗下藝人社交網路，強制旗下藝人將IG、臉書、小紅書等社交平台的帳號密碼交由公司「中央管轄」，對此，TVB火速發聲回應。...…", "link": "https://ent.ltn.com.tw/news/breakingnews/5396601", "published_my": "260408 102129", "site": "ltn", "label": "即時"}
{"title": "健康網》食在不安 營養師談危險溫度帶：細菌倍數生長", "summary": "〔健康頻道／綜合報導〕高雄正義市場的潤餅攤引發140人食物中毒，其中31人住院、10人急診待床、8人留觀中，其中12人檢出沙門氏菌。包含此案在內，近期不少食物中毒等食安問題頻傳，營養師林俐岑說明...…", "link": "https://health.ltn.com.tw/article/breakingnews/5396073", "published_my": "260408 102132", "site": "ltn", "label": "即時"}
{"title": "焦點股》00631L：台股大漲千點 正2漲幅逾1成", "summary": "受到美伊暫時停戰消息影響，台股開盤大漲逾千點，截至10點為止，上漲1370.12點，漲幅4.12%，不過，槓桿型的元大台灣50正2（00631L）更猛，股價上漲2.14元...…", "link": "https://ec.ltn.com.tw/article/breakingnews/5396621", "published_my": "260408 102220", "site": "ltn", "label": "即時"}
{"title": "告別連日暴雨！今起鋒面減弱高溫上看30度 下波變天時間曝光", "summary": "<br />\n<br />\nNewtalk新聞 <br />\n<br />\n<p>從清明連假以來，全台遭受強勁春雨的襲擊連日暴雨。不過氣象專家吳德榮指出，今(8)日白天起鋒面將逐漸減弱，雖然仍有短暫降雨機率，但天氣會逐漸好轉；明天到14日南方氣團偏強，高溫上看30度；15日下一波鋒面靠近，但目前預報顯示強度弱、影響輕微。</p><br />\n<p>氣象專家吳德榮指出，今日白天起鋒面減弱，局部地區偶有短暫降雨的機率；各地漸好轉、氣溫升，白天北舒適、中南略偏熱。各地區氣溫如下：北部18至26度、中部19至30度、南部20至33度、東部18至31度。</p><br />\n<p>明日起至14日南方氣團偏強，鋒面北移、在長江流域至華南一帶徘徊，台灣天氣穩定、白天「熱如盛夏」，高溫大多落到26到30度。至於下波鋒面將在15、16日接近，但強度弱、影響很輕微。</p><br />\n<p>此外，各國模式持續模擬，週末起在關島東南方有「熱帶擾動」發展，各國模擬的動向雖有分岐，但皆對台無威脅、與「4月颱、不侵台」的氣候資料相符合。</p><p><p>延伸閱讀：</p></p><p><p><a href=\"https://newtalk.tw/news/view/2026-04-08/1028577\" target=\"_blank\">4縣市大雨特報！今白天起各地降雨趨緩漸轉多雲 北台灣氣溫稍回升</a></p></p><p><p><a href=\"https://newtalk.tw/news/view/2026-04-08/1028601\" target=\"_blank\">回文詩》四國 最御崎寺 </a></p></p><p><p><a href=\"https://newtalk.tw/news/view/2026-04-06/1028265\" target=\"_blank\">雨神最後一擊！鋒面夾雷雨襲台3天 4/9起全台放晴一週</a></p></p><p><p><a href=\"https://newtalk.tw/news/view/2026-04-06/1028304\" target=\"_blank\">再忍一天！明鋒面通過就放晴「高溫飆33度」 未來一週天氣一圖看</a></p></p><p><p><a href=\"https://newtalk.tw/news/view/2026-04-07/1028368\" target=\"_blank\">鋒面到北台灣了！氣象專家：台南以北都要留意雷雨或短時大雨</a></p></p>", "link": "https://newtalk.tw/news/view/2026-04-08/1028604", "published_my": "260408 102233", "site": "newtalk", "label": "全部"}
{"title": "鄭麗文訪中稱台灣人可以擺脫悲情 基進：中國才需擺脫國恥的執念", "summary": "", "link": "https://www.setn.com/News.aspx?NewsID=1819365", "published_my": "260408 102300", "site": "setn", "label": "setn"}
{"title": "屏縣補助私有建物耐震評估 每案最高補助40萬元", "summary": "近年地震頻繁發生，為提升民眾對自有住宅耐震能力的重視，強化居住安全，屏東縣政府推動私有建築物耐震評估補助措施，其中初步評估每案最高補助1萬5000元，詳細評估每案最高補助40萬...…", "link": "https://news.ltn.com.tw/news/life/breakingnews/5396581", "published_my": "260408 102342", "site": "ltn", "label": "即時"}
{"title": "凍漲！乾干貝大漲3成 鹿港老店干貝粽宣布今年不漲", "summary": "今年乾的干貝大漲3成，但彰化縣鹿港知名老店「木生海鮮會館」長年熱賣的干貝粽，老闆許看霸氣宣布「今年凍漲」，要漲價也是明年的事，認為少賺一點就好！\n\n    許看指出，甘貝粽...…", "link": "https://news.ltn.com.tw/news/life/breakingnews/5396622", "published_my": "260408 102417", "site": "ltn", "label": "即時"}
{"title": "LINE盜帳風波台灣大哥大接16件申訴 林宜敬：雙方漏洞疊加釀資安破口", "summary": "台灣LINE用戶於3月底爆發大規模帳號遭盜事件，數位發展部長林宜敬今（8）日赴立法院交通委員會進行業務報告並備質詢，針對國民黨立委萬美玲關切的處理進度作出回應。\n\n\n林宜...…", "link": "https://ec.ltn.com.tw/article/breakingnews/5396616", "published_my": "260408 102429", "site": "ltn", "label": "即時"}
{"title": "迎接母親節！「這類人」搭高鐵享5折優惠 後天起開放購票", "summary": "", "link": "https://www.setn.com/News.aspx?NewsID=1819359", "published_my": "260408 102500", "site": "setn", "label": "setn"}
{"title": "吊車大王胡漢龑女兒正臉曝光  網驚呆：笑容把我帶走", "summary": "64歲竹北「吊車大王」胡漢龑，是機械起重工程董事長，年收入達30億，擁有4位妻子及14位孩子的他，鮮少對外透露家人的現況，近日，他的其中1位女兒上了中古車買賣網紅「阿慈車庫」頻道賣車，姣好面貌曝光後，", "link": "https://www.chinatimes.com/realtimenews/20260408001441-260404", "published_my": "260408 102600", "site": "chinatimes", "label": "chinatimes"}
{"title": "焦點股》光洋科：台積電強勢 股價聯袂勁揚", "summary": "今日台積電（2330）強勢表態，貴金屬與靶材大廠光洋科（1785）也開高走高，該公司並看好營運有望持續成長，近10時20分，光洋科股價上漲6.2元或6.9%，暫報96元，...…", "link": "https://ec.ltn.com.tw/article/breakingnews/5396627", "published_my": "260408 102607", "site": "ltn", "label": "即時"}
{"title": "鄭麗文訪中隨行成員曝光！林俊憲揪「1共通點」：現代版「議和團」", "summary": "", "link": "https://www.setn.com/News.aspx?NewsID=1819296", "published_my": "260408 102700", "site": "setn", "label": "setn"}
{"title": "電子作戰中心預財士A走同袍工作獎金 侵占1萬3500元被依貪污起訴", "summary": "25歲方姓男子在國防部資通電軍指揮部電子作戰中心擔任預財士，卻利用職務之便侵占同袍工作獎金，2022年7月至12月間總計侵吞1萬3500元，被桃園地檢署偵辦後，依貪污治罪條例侵...…", "link": "https://news.ltn.com.tw/news/society/breakingnews/5396605", "published_my": "260408 102813", "site": "ltn", "label": "即時"}
{"title": "鄭麗文「和平之旅」率團訪中 中國昨出動12機艦擾台", "summary": "中國國民黨主席鄭麗文昨起率團訪中展開所謂「和平之旅」，然而中共解放軍仍持續對台遂行軍事施壓及灰色地帶襲擾，除近日無預警在外海劃設長達40天、5區域的禁飛區外，國防部今（8）日表...…", "link": "https://news.ltn.com.tw/news/def/breakingnews/5396617", "published_my": "260408 102817", "site": "ltn", "label": "即時"}
{"title": "中央+北市加碼  育兒家庭月租補助破萬元", "summary": "台北市政府都發局針對在台北市一般租屋市場租屋的「單身青年」「已婚青年家庭」與「育兒家庭」，在獲准中央「300億元擴大租金補貼專案」並在台北市設籍的前提下，加碼推出「台北幸福租-...…", "link": "https://news.ltn.com.tw/news/life/breakingnews/5396629", "published_my": "260408 102825", "site": "ltn", "label": "即時"}
{"title": "鄭麗文率團訪中 國安局示警中共「2個分化」劍指軍購案", "summary": "國民黨主席鄭麗文率團訪問中國展開「和平之旅」，外界關注「鄭習會」是否將如期登場。國安局長蔡明彥今（8）日受訪指出，國安局不適合評論國內政黨活動，但從國安角度分析，中共對台策略核...…", "link": "https://news.ltn.com.tw/news/politics/breakingnews/5396594", "published_my": "260408 102906", "site": "ltn", "label": "即時"}
{"title": "自由開講》戰時韌性建築之文化資產價值：水陸雙動脈節點「蔡金木宅」之指定理由", "summary": "一、 背景與核心論述：水陸雙動脈與「決戰型住宅」的生存空間轉譯\n\n\n台北盆地南緣之空間發展，深受「瑠公圳（水路）」與1921年通車的「萬新鐵路（陸路煤礦運輸）」兩大產業動脈所形塑。位於...…", "link": "https://talk.ltn.com.tw/article/breakingnews/5393999", "published_my": "260408 103000", "site": "ltn", "label": "即時"}
{"title": "特斯拉股價恐崩60％！小摩「極度看空」應不惜一切避開", "summary": "摩根大通發出對特斯拉的嚴重警告，認為其股價嚴重背離基本面，將目標價降為145美元，等於從現有水準下殺60%，呼籲投資人保持謹慎，應不惜一切避開特斯拉股票。特斯拉是今年美股七巨頭中股價表現最差的公司，今", "link": "https://www.chinatimes.com/realtimenews/20260408001602-260410", "published_my": "260408 103000", "site": "chinatimes", "label": "chinatimes"}
{"title": "狗公園認養新模式！免派員維護 捐款、捐物資也能成為認養人", "summary": "台北市狗公園以往的認養單位，需要派員維護園區。台北市動物保護處指出，今年3月15日修正台北市狗運動公園及狗活動區認養模式，增加捐款或捐贈物資也能做為認養狗公園的方式。\n\n動...…", "link": "https://news.ltn.com.tw/news/life/breakingnews/5396618", "published_my": "260408 103020", "site": "ltn", "label": "即時"}
{"title": "成大接獲炸彈恐嚇信 初查寄信地在境外", "summary": "成功大學校方電子信箱於7日接獲恐嚇電子郵件，疑有人要在校園內放置爆裂物，校方立即通報南市警一分局，警方派遣警力、帶相關檢測器材到校做安全檢查，並未發現任何危險爆裂物品，持續對成...…", "link": "https://news.ltn.com.tw/news/society/breakingnews/5396631", "published_my": "260408 103028", "site": "ltn", "label": "即時"}
{"title": "醫驚23歲年輕人大腸長腺瘤！急喊「這3種肉」別吃：一級致癌物", "summary": "", "link": "https://www.setn.com/News.aspx?NewsID=1819366", "published_my": "260408 103100", "site": "setn", "label": "setn"}
{"title": "現在適合買黃金嗎？專家預測上看6000美元、關鍵原因全解析", "summary": "〔財經頻道／綜合報導〕嘉貝利基金（Gabelli Funds）旗下「嘉貝利黃金基金」（GLDAX）共同投資組合經理人曼奇尼（Chris Mancini）表示，隨著伊朗戰爭持續，以及歐洲與美國同步...…", "link": "https://ec.ltn.com.tw/article/breakingnews/5396477", "published_my": "260408 103134", "site": "ltn", "label": "即時"}
{"title": "開鍘李貞秀民眾黨中評會將延期 他酸：是被交代鄭麗文訪中不能動手吧", "summary": "<br />\n<br />\nNewtalk新聞 <br />\n<br />\n<p>民眾黨立委李貞秀因先前自爆，新竹市長高虹安拿前民眾黨主席柯文哲700萬元，遭移送中評會處置。近日更遭踢爆，李貞秀正是當年檢舉高虹安涉詐助理費證人之一。原訂民眾黨中評會將於9日開會議處，但傳出會議會延後到13日。對此政治工作者周軒昨（7）日就酸：「我看民眾黨是被交代不能在鄭麗文還在中國的時候動手吧？」</p><br />\n<p>李貞秀日前於直播中爆料，高虹安拿柯文哲700萬元，引起白營及其支持者反彈。儘管她事後道歉，但仍澆不息黨內怒火，民眾黨中評會也立案調查。除此之外，李貞秀近日更背踢爆，李貞秀正式當年檢舉高虹安涉詐助理費案證人之一，並與曾代表民眾黨參選竹縣竹北市長，爾後遭因酒駕遭開除黨籍的林冠年關係密切，讓不少民眾黨支持者不滿，紛紛要求對李貞秀開鍘。</p><br />\n<p>民眾黨中評會原定9日開會議處李貞秀之案，而李貞秀昨日受訪被問及此事時，表示尊重中評會獨立裁決。然而，傳出9日召開中評會將延至13日。</p><br />\n<p>對此，民眾黨中評會主委李偉華證實會議延期一事，並聲稱因為有委員出國，致使會議延期。而李偉華也坦言，站在中評會立場，很難就李貞秀之失言就做出除名處分，並指若做出除名處分，將說服外界相信民眾黨是有制度的政黨。</p><br />\n<p>對此，周軒就酸：遇到柯文哲不是馬上就可以改規定？遇到李貞秀就「委員出國」？他也質疑：「我看民眾黨是被交代不能在鄭麗文還在中國的時候動手吧？」</p><p><p>延伸閱讀：</p></p><p><p><a href=\"https://newtalk.tw/news/view/2026-04-07/1028373\" target=\"_blank\">柯文哲自詡雍正帝...李貞秀自稱鈕祜祿氏 前白營高層：妳是要跟正宮陳佩琪「搶位」？</a></p></p><p><p><a href=\"https://newtalk.tw/news/view/2026-04-07/1028409\" target=\"_blank\">李貞秀幹嘛不「躺平」就好？她曝：中評會開除李貞秀將引爆兩顆深水炸彈！</a></p></p><p><p><a href=\"https://newtalk.tw/news/view/2026-04-06/1028290\" target=\"_blank\">蔣中正忌日喊「和平才能躺平」 他酸國民黨：反共路線已隨入土</a></p></p><p><p><a href=\"https://newtalk.tw/news/view/2026-04-07/1028411\" target=\"_blank\">藍營內部警訊炸裂！王家俊曝「死亡紀事」：鄭麗文撐過兩關反成2028致命關鍵</a></p></p><p><p><a href=\"https://newtalk.tw/news/view/2026-04-07/1028481\" target=\"_blank\">吳瑟致觀點》鄭麗文赴中「躺平」無法換得台灣的國家安全</a></p></p>", "link": "https://newtalk.tw/news/view/2026-04-08/1028610", "published_my": "260408 103144", "site": "newtalk", "label": "全部"}
{"title": "鄭麗文赴中挨轟！侯友宜喊「以民為念」：堅持自由民主方向永遠不變", "summary": "", "link": "https://www.setn.com/News.aspx?NewsID=1819370", "published_my": "260408 103200", "site": "setn", "label": "setn"}
{"title": "IVE門票今開賣！粉絲爆「搶票中突被鎖帳號」 拓元強硬發聲回應了", "summary": "", "link": "https://www.setn.com/News.aspx?NewsID=1819367", "published_my": "260408 103200", "site": "setn", "label": "setn"}
{"title": "自家人都質疑！檢察總長人事  高檢主任批徐錫祥辦案資歷不足", "summary": "最高檢察署檢察總長邢泰釗任期將屆滿，賴清德總統提名最高檢主任檢察官徐錫祥為新任檢察總長，正值立法院審查徐人事案之際，台灣高檢署主任檢察官陳宏達8日撰文，質疑徐雖曾歷任多個地檢署檢察長、法務部政次，卻未", "link": "https://www.chinatimes.com/realtimenews/20260408001634-260402", "published_my": "260408 103200", "site": "chinatimes", "label": "chinatimes"}
{"title": "快訊／美伊停火2週！《美聯社》：伊朗、阿曼將收「荷莫茲海峽」過路費", "summary": "", "link": "https://www.setn.com/News.aspx?NewsID=1819368", "published_my": "260408 103300", "site": "setn", "label": "setn"}
{"title": "5歲女童單眼視力1.0 竟藏弱視危機 醫：瞇眼是警訊", "summary": "宜蘭縣1名5歲女童在校園篩檢時發現視力不良，經國立陽明交通大學附設醫院眼科門診檢查後，女童右眼視力僅0.4，且伴隨350度高度散光，確診為「弱視」，令家長驚訝的是孩子左眼視力達1.0，完全沒表現出看不", "link": "https://www.chinatimes.com/realtimenews/20260408001567-260418", "published_my": "260408 103400", "site": "chinatimes", "label": "chinatimes"}
{"title": "離譜畫面曝！2名大學生研製「高爆火藥」炸校園被押…現場滿目瘡痍", "summary": "", "link": "https://www.setn.com/News.aspx?NewsID=1819369", "published_my": "260408 103400", "site": "setn", "label": "setn"}
{"title": "「傘兵節」傳揚忠義精神 落實科技練兵", "summary": "今日是國軍「傘兵節」。回顧傘兵部隊成軍以來，不論在豫東會戰、東山島戰役中，均展現出無畏犧牲、克敵制勝的堅強戰志。如今面對現代化戰場與嚴峻敵情威脅，這支擁有「忠義驃悍」優良傳統的勁旅，積極結合VR操傘", "link": "https://www.chinatimes.com/realtimenews/20260408000075-260417", "published_my": "260408 103500", "site": "chinatimes", "label": "chinatimes"}
{"title": "基隆河濫倒廢油害15萬戶汙染    元凶 28人、4公司遭起訴", "summary": "基隆河八堵抽水站附近去年發生油汙，導致約15萬戶基隆市及新北市汐止區自來水飄出汽油味。環檢警查獲，業者故意中斷清運車輛GPS，直接將含油廢水排入基隆河，造成嚴重汙染，還勾結合法處理、再利用機構，開具廢", "link": "https://www.chinatimes.com/realtimenews/20260408001546-260402", "published_my": "260408 103500", "site": "chinatimes", "label": "chinatimes"}
{"title": "索粉埋單嗎？Sony 新旗艦手機 Xperia 1 VIII 諜照流出　設計改超大", "summary": "Sony 旗艦手機 Xperia 1 系列憑藉簡潔的日系設計，長期深受索粉喜愛，且該系列已長達 6 年未進行外型大改版。不過根據爆料帳號 @INSIDERSONY 釋出最新 CAD 工程設計圖，Sony 疑似將替 Xperia 1 VIII 的相機帶來全新設計。…", "link": "https://3c.ltn.com.tw/news/65611", "published_my": "260408 103500", "site": "ltn", "label": "即時"}
{"title": "關島擾動最快週末成颱 吳聖宇：預報將是大而強的颱風", "summary": "鋒面南移減弱，不過西半部仍有些水氣，今（8日）中午前西半部不時會有些短暫陣雨機會，午後雨勢將會趨緩，明（9日）起開始轉為穩定晴朗的炎熱天氣；而遠洋也開始有熱帶系統正在醞釀，關島東...…", "link": "https://news.ltn.com.tw/news/life/breakingnews/5396600", "published_my": "260408 103659", "site": "ltn", "label": "即時"}
{"title": "慘！駐韓美軍孕妻早產被踢皮球4小時 雙胞胎嬰1死1命危", "summary": "南韓大邱市消防安全本部7日透露，1名駐韓美軍士兵的懷孕妻子2月28日深夜在大邱市東區飯店出現早產跡象，隨後被多間醫院踢皮球4小時拒收，導致雙胞胎嬰兒1死1命危。\n\n據《韓聯社...…", "link": "https://news.ltn.com.tw/news/world/breakingnews/5396554", "published_my": "260408 103713", "site": "ltn", "label": "即時"}
{"title": "徐春鶯涉國安組織滲透  她喊話柯文哲說清楚：民眾黨有沒有跟孫憲、楊文濤見過面？", "summary": "<br />\n<br />\nNewtalk新聞 <br />\n<br />\n<p>曾列民眾黨不分區立委安全名單的中配徐春鶯，遭新北地檢署依反滲透法等罪起訴，徐7日開庭時只坦承地下匯兌、詐貸，不認犯反滲透法。對此，政治評論員吳靜怡今（8）日喊話，民眾黨主席柯文哲不用出來解釋跟徐春鶯的關係嗎？孫憲試圖滲透台灣已久，「被紅色滲透的紅蔥頭柯文哲出來講，民眾黨有沒有高層幹部跟孫憲、楊文濤見過面？」</p><br />\n<p>民眾黨新住民委員會前主委徐春鶯，遭新北地檢署依反滲透法等罪起訴，檢方指她曾向國內政黨索要不分區立委席次，並查出，徐春鶯涉受中共指示為柯文哲站台等，起訴書也揭露上海市統促會副主任孫憲問徐春鶯「李貞秀接班應該沒問題了吧？」</p><br />\n<p>根據起訴書，徐春鶯涉長期密切聯繫中共民政部海峽兩岸婚姻家庭服務中心主任楊文濤、孫憲，並彙報台灣政情選情。徐春鶯7日開庭時不認犯反滲透法，並稱與中共官員對話內容只是閒聊，法官當庭勘驗徐春鶯與孫憲微信對話紀錄顯示，孫憲掌握台灣政情，包括京華城案爆發後兩人討論民眾黨內部動態；對話顯示，孫憲曾問徐春鶯能否成立社區團體作為兩岸社區論壇對口單位，徐春鶯稱「明白」，孫憲還提醒「防範監聽」。</p><br />\n<p>吳靜怡發文提及，徐春鶯找集智公司協助中共高幹孫憲虛偽填寫短期商務活動，獲准在2025年10月14日到24日間來台，長達10天期間，徐春鶯不只有新住民發展協會身分，更涉及國安組織滲透中，時任最敏感的「台灣民眾黨新住民委員會主委」一職，甚至孫憲對李貞秀有高度興趣，難道徐春鶯沒有任何約訪民眾黨的動作嗎？</p><br />\n<p>吳靜怡質疑，孫憲試圖滲透台灣已久，接觸到醫療界的企業該不會也跟民眾黨曾經不分區名單也正巧有關係？接觸到的宜蘭社團團長該不會也正好是民眾黨核心幹部？環環相扣的結果，柯文哲不用出來跟社會解釋，徐春鶯跟你的關係嗎？「柯文哲敢不敢擔保，徐春鶯有收紅錢但李貞秀沒有拿任何一塊錢？黃珊珊至今卻不見蹤影！」</p><p><p>延伸閱讀：</p></p><p><p><a href=\"https://newtalk.tw/news/view/2026-04-08/1028588\" target=\"_blank\">徐春鶯的「閒聊」讓人毛骨悚然！他曝：接收統戰指令  精準回報柯文哲案情</a></p></p><p><p><a href=\"https://newtalk.tw/news/view/2026-04-07/1028437\" target=\"_blank\">李貞秀再度空氣質詢又哽咽 他諷：保母從陳智菡升級為立法院長韓國瑜</a></p></p><p><p><a href=\"https://newtalk.tw/news/view/2026-04-07/1028381\" target=\"_blank\">陳佩琪嗆赴監院查扁帽工廠  律師：陳水扁醫療小組柯文哲、陳昭姿竟惡搞自己病人？</a></p></p><p><p><a href=\"https://newtalk.tw/news/view/2026-04-07/1028409\" target=\"_blank\">李貞秀幹嘛不「躺平」就好？她曝：中評會開除李貞秀將引爆兩顆深水炸彈！</a></p></p><p><p><a href=\"https://newtalk.tw/news/view/2026-04-07/1028558\" target=\"_blank\">最小才8歲！台中棒球教練性侵猥褻82童受害  議員轟盧秀燕冷血包庇教育局</a></p></p>", "link": "https://newtalk.tw/news/view/2026-04-08/1028605", "published_my": "260408 103729", "site": "newtalk", "label": "全部"}
{"title": "《美股》消息面：全面摧毀伊朗喊卡；川普：雙向停火2周", "summary": "消息面：　●美國總統川普當地時間七日宣布，原訂要對伊朗基礎建設的毀滅計畫，現在暫停執行兩星期。在美以聯手攻打伊朗五周之後，川普在自己的社群平台Truth Social上說，之所以停火兩星期，是因為伊朗", "link": "https://www.chinatimes.com/realtimenews/20260408001688-260410", "published_my": "260408 103900", "site": "chinatimes", "label": "chinatimes"}
{"title": "膽大包天！千噸廢料堆國道警察隊部旁 地主等3人遭訴求重刑", "summary": "苗栗縣造橋鄉雙鶴山一處私人鐵皮廠房，位處國道二隊大隊部旁，但肆無忌憚，非法堆置了1500公噸的汽車廢料廢棄物，一旦崩落，國道二隊恐遭殃。苗栗地檢署全案偵結，依違反廢棄物清理法提...…", "link": "https://news.ltn.com.tw/news/society/breakingnews/5396625", "published_my": "260408 103959", "site": "ltn", "label": "即時"}
{"title": "新店「清六食堂」中毒44人！侯友宜「該法辦就移送」：全盤關懷受害民眾", "summary": "", "link": "https://www.setn.com/News.aspx?NewsID=1819379", "published_my": "260408 104000", "site": "setn", "label": "setn"}
{"title": "美伊停火大利多！亞股狂漲慶祝 韓股漲逾6%觸發熔斷", "summary": "", "link": "https://www.setn.com/News.aspx?NewsID=1819342", "published_my": "260408 104000", "site": "setn", "label": "setn"}
{"title": "搭飛機新制今上路 違規最重罰10萬", "summary": "為配合國際民航組織（ICAO）最新規範，交通部民航局宣布，今起全面實施行動電源新制，規定每位旅客最多只能隨身攜帶2個行動電源，且禁止在飛行途中充電，若旅客違規攜帶，可依《民用航空法》開罰2至10萬元。", "link": "https://www.chinatimes.com/realtimenews/20260408001615-260405", "published_my": "260408 104000", "site": "chinatimes", "label": "chinatimes"}
{"title": "板橋語言治療師侵犯8身心障礙童 診所：深感震驚與歉疚 該師永不錄用", "summary": "", "link": "https://www.setn.com/News.aspx?NewsID=1819376", "published_my": "260408 104000", "site": "setn", "label": "setn"}
{"title": "《半導體》看好AI強勁成長！美系外資上調台積電目標價至2750元", "summary": "台積電(2330)今（8）日股價強漲逾4%，展現超強氣勢。美系外資最新報告上調目標價，由原先的2600元調升至2750元，看好強勁的AI需求將支撐台積電多年的成長，並有助其毛利率。另一家美系外資同時也", "link": "https://www.chinatimes.com/realtimenews/20260408001690-260410", "published_my": "260408 104000", "site": "chinatimes", "label": "chinatimes"}
{"title": "楊珍妮又臨時缺席立院 白委諷：我不能霸凌不讓妳請病假", "summary": "<br />\n<br />\nNewtalk新聞 <br />\n<br />\n<p>立法院經濟委員會今（8日）邀經濟部、財政部、主計總處及行政院經貿談判辦公室就台美關稅協定相關議題進行專案報告，但涉入行政院經貿辦副總談判代表顏慧欣霸凌案的行政院經貿談判辦公室總代表楊珍妮卻臨時請病假。讓擔任擔任會議主席的民眾黨籍召委洪毓祥諷刺：「我個人覺得是蠻嚴重的，不要欺負新科立委耶！但我不能霸凌妳，說不讓妳請病假。」</p><br />\n<p>會議開始後，洪毓祥介紹在場官員時，所介紹的行政院經貿談判辦公室代表，為資深談判代表兼執行秘書徐崇欽。</p><br />\n<p>洪毓祥隨後特別聲明說，因為行政院經貿談判辦公室的總代表楊珍妮臨時請病假，「我是還沒收到請假單，我個人覺得是蠻嚴重的，不要欺負新科立委耶！但我不能霸凌妳，說不讓妳請病假。所以我是覺得只此一次，下不為例。」</p><br />\n<p>洪毓祥補充，他到昨天晚上都沒收到假單，連立法院議事處都沒收到，直到今天早上，才有人跑來跟他講，所以先跟大家說明狀況。</p><p><p>延伸閱讀：</p></p><p><p><a href=\"https://newtalk.tw/news/view/2026-04-08/1028605\" target=\"_blank\">徐春鶯涉國安組織滲透  她喊話柯文哲說清楚：民眾黨有沒有跟孫憲、楊文濤見過面？</a></p></p><p><p><a href=\"https://newtalk.tw/news/view/2026-04-08/1028594\" target=\"_blank\">中國劃5空域保留區  蔡明彥：到川習會前一週、意在測試美國 </a></p></p><p><p><a href=\"https://newtalk.tw/news/view/2026-04-08/1028588\" target=\"_blank\">徐春鶯的「閒聊」讓人毛骨悚然！他曝：接收統戰指令  精準回報柯文哲案情</a></p></p><p><p><a href=\"https://newtalk.tw/news/view/2026-04-08/1028603\" target=\"_blank\">繞過修憲下修18歲選舉權？ 綠委曝主因：修法為取得釋憲門票</a></p></p><p><p><a href=\"https://newtalk.tw/news/view/2026-04-07/1028414\" target=\"_blank\">卓榮泰步上台表拒李貞秀質詢  韓國瑜：請行政院長尊重憲法質詢權</a></p></p>", "link": "https://newtalk.tw/news/view/2026-04-08/1028620", "published_my": "260408 104040", "site": "newtalk", "label": "全部"}
{"title": "影》妻一句話點醒！船長重返舊海域 276公斤「第一鮪」到手", "summary": "宜蘭縣黑鮪季正式開胡！蘇澳籍漁船「全昌隆168號」船長林宜俊7日凌晨捕獲重達276公斤黑鮪魚，今（8）日完成鑑定程序，確認符合「第一鮪」資格，成功連莊奪下蘇澳頭彩。區漁會表示，後續將擇日進行拍賣，備受", "link": "https://www.chinatimes.com/realtimenews/20260408001605-260405", "published_my": "260408 104100", "site": "chinatimes", "label": "chinatimes"}
{"title": "鐵工孝子遭砂石車連環撞奪命！兄悲曝：年邁雙親怎接受", "summary": "南投縣竹山鎮投100線昨（7）日發生4車連環撞事故，慘釀1死2傷，死者為48歲楊姓小貨車男駕駛。據了解，楊男從事鐵工行業，未婚與父母同住，人勤奮上進好相處，對雙親更是照顧得無微不至，哥哥聽到此噩耗悲慟", "link": "https://www.chinatimes.com/realtimenews/20260408001678-260402", "published_my": "260408 104100", "site": "chinatimes", "label": "chinatimes"}
{"title": "環管署傳霸凌！ 署長顏旭明澄清：旁人檢舉、當事人否認", "summary": "<br />\n<br />\nNewtalk新聞 <br />\n<br />\n<p>立法院今（8）日召開社會福利及衛生環境委員會，國民黨立委陳菁徽在質詢時指出，接獲兩起環境管理署的霸凌陳情案。對此，環管署長顏旭明澄清，霸凌檢舉人非案件當事人，當事人經調查也表示「並無霸凌不適」；環境部長彭啓明也承諾，將在一個月內提供兩起霸凌案的報告說明。</p><br />\n<p>陳菁徽指出，近日收到消息，環管署去年8月發生兩起霸凌檢舉案。第一起案件為環管署數位執法科的孫姓科長，據陳情，他在稽查同仁的外套採購案時，因為經費控管問題，而在主管會議中直接大罵督察科長，導致無法合作、工作互推。第二起為環評科長，因為公文超過四個小時無法改分，而怒駡登記桌女性同仁，甚至在下班後傳訊息言語霸凌，造成同仁落淚。</p><br />\n<p>陳菁徽質疑，陳情案至今已近8個月，環管署是否有進入調查程序？對此，彭啓明解釋，案件因當事人後續表明自己並不認為「有被霸凌」，相關情況會再追查；他也提到，在公務機關有時候因主管嚴厲而出現的一些不舒服案件數量蠻多的，因此，內部需要有一定的程序做處理。</p><br />\n<p>顏旭明則澄清，該陳情人並非「被霸凌者」，而是看見同仁被駡而向上反映，署內後續也啟動相關霸凌會議與教育，當事人經調查也表示，「我們沒有被霸凌啦，如果有的話會反映。」之後，也請外部人員至組內進行教育訓練，9月也深入做全組調查，相關同仁也未反映霸凌事情。「或許我們在內部教育訓練需提醒講話的聲音要客客氣氣、要互相尊重。」</p><br />\n<p>陳菁徽除了要求提供調查報告，也提到「假使兩位科長沒有錯，我們也應該還兩位科長清白」。彭啓明則承諾，將在一個月內提供兩起霸凌案的調查報告。</p><p><p>延伸閱讀：</p></p><p><p><a href=\"https://newtalk.tw/news/view/2026-04-02/1027820\" target=\"_blank\">再被爆職場霸凌 駐美大使俞大㵢首回應：對子虛烏有指控感到遺憾</a></p></p><p><p><a href=\"https://newtalk.tw/news/view/2026-04-02/1027807\" target=\"_blank\">遭控霸凌狂換20名清潔工！  俞大㵢妻發聲駁斥</a></p></p><p><p><a href=\"https://newtalk.tw/news/view/2026-04-02/1027772\" target=\"_blank\">楊珍妮需為顏慧欣霸凌案調職？行政院：尊重外部委員調查 </a></p></p><p><p><a href=\"https://newtalk.tw/news/view/2026-04-07/1028507\" target=\"_blank\">澳洲授勳最多「國家英雄」涉殺害平民遭逮 被指控5項「戰爭罪」</a></p></p><p><p><a href=\"https://newtalk.tw/news/view/2026-04-08/1028620\" target=\"_blank\">楊珍妮又臨時缺席立院 白委諷：我不能霸凌不讓妳請病假　</a></p></p>", "link": "https://newtalk.tw/news/view/2026-04-08/1028597", "published_my": "260408 104143", "site": "newtalk", "label": "全部"}
{"title": "掛超鹹濕布條吸睛攬客  台中一中街射氣球攤老闆慘了", "summary": "張姓男子在114年農曆春節期期間，在台中一中街年貨大街擺射氣球攤，但為了吸引客人，竟掛上大型帆布條及看板，寫著「射在你Ｘ上」、「男人喜歡大ＸＸ」、「女人喜歡大ＸＸ」，甚至還有露股的鹹濕言語，警方獲報後", "link": "https://www.chinatimes.com/realtimenews/20260408001679-260402", "published_my": "260408 104200", "site": "chinatimes", "label": "chinatimes"}
{"title": "美伊和談10日將於巴基斯坦舉行! 巴國多方奔走 「這2方」最後介入敲定", "summary": "<br />\n<br />\nNewtalk新聞 <br />\n<br />\n<p>據伊朗《邁赫爾通訊社》今 ( 8 ) 日淩晨援引伊朗最高國家安全委員會秘書處聲明報導，與美國的談判將於 10 日在巴基斯坦首都伊斯蘭馬巴德開始，為期兩周。</p><br />\n<p>在距離美國總統川普設定的「最後期限」不到一個半小時，美國與伊朗分別宣佈同意停火。</p><br />\n<p>美國《紐約時報》4月7日報導，3 名伊朗官員透露，停火協定達成之前，巴基斯坦曾展開密集外交斡旋，中國也在最後時刻出面介入，敦促伊朗保持克制、展現靈活性以緩和局勢。</p><br />\n<figure class=\"news_img open-gallery clearfix\"><img alt=\" 巴基斯坦是這次美伊和談斡旋的主力方，圖為巴國陸軍參謀長穆尼爾(左)。 圖 : 翻攝自沉浮歐羅巴 \" class=\"cjImg img832940\" height=\"443\" src=\"https://s.newtalk.tw/album/news/1009/693693063da68.jpg\" title=\" 巴基斯坦是這次美伊和談斡旋的主力方，圖為巴國陸軍參謀長穆尼爾(左)。 圖 : 翻攝自沉浮歐羅巴 \" width=\"670\" /> <figcaption class=\"mainpic clearfix\" style=\"clear: both;\"> 巴基斯坦是這次美伊和談斡旋的主力方，圖為巴國陸軍參謀長穆尼爾(左)。 圖 : 翻攝自沉浮歐羅巴 </figcaption></figure><br />\n<p>根據《美聯社》報導，一位參與斡旋國家的官員透露，在「最後期限」逼近之際，中方以及美國副總統范斯分別促成伊美達成協議。</p><br />\n<p>其中，中方成功幫助說服伊朗同意停火。此前，中方主要通過巴基斯坦、土耳其、埃及等中間方開展工作。此外，在美國時間 7 日晚間，由於陷入僵局，正在匈牙利訪問的范斯也被納入協調。</p><br />\n<p>目前，儘管美國和伊朗停火已生效，以媒報導稱，以色列「仍在持續打擊伊朗」。另據《伊朗國家電視臺》報導，伊朗最高領袖穆傑塔巴·哈梅內伊已向全軍下達停火命令，但停火命令傳達至各作戰單元可能需要一定時間。</p><br />\n<figure class=\"news_img open-gallery clearfix\"><img alt=\" 川普指派范斯(右)主責伊朗談判事宜。 圖：翻攝自 @cryptorover X 帳號 \" class=\"cjImg img851126\" height=\"360\" src=\"https://s.newtalk.tw/album/news/1024/69ae84bb413e2.jpg\" title=\" 川普指派范斯(右)主責伊朗談判事宜。 圖：翻攝自 @cryptorover X 帳號 \" width=\"360\" /> <figcaption class=\"mainpic clearfix\" style=\"clear: both;\"> 川普指派范斯(右)主責伊朗談判事宜。 圖：翻攝自 @cryptorover X 帳號 </figcaption></figure><br />\n<p>當地時間 7 日，美國總統川普在社交媒體平臺發文確認，同意暫停對伊朗的轟炸和襲擊行動，為期兩周。川普說，巴基斯坦總理夏巴茲及陸軍元帥穆尼爾在通話中請求他，暫緩當天晚上擬對伊朗實施的「毀滅性打擊」。以伊朗同意全面、立即、安全開放荷姆茲海峽為前提，川普同意暫停對伊朗的轟炸與軍事攻擊。</p><br />\n<p>川普稱，此次將是雙向停火。他聲稱，美方所有軍事目標均已達成並超額完成，且與伊朗就長期和平及中東地區穩定的最終協定談判已取得重大進展。</p><br />\n<p>川普透露，美方收到伊朗提出的十點方案，認為其可作為談判的可行基礎。美伊雙方已就過往幾乎所有爭議點達成共識，兩周時間將足以最終敲定並完善協議。</p><p><p>延伸閱讀：</p></p><p><p><a href=\"https://newtalk.tw/news/view/2026-04-06/1028298\" target=\"_blank\">誤認是以色列軍艦？黎巴嫩真主黨搞烏龍 英國軍艦遭飛彈擊中受損</a></p></p><p><p><a href=\"https://newtalk.tw/news/view/2026-04-06/1028329\" target=\"_blank\">美伊最新停火協議曝光! 伊棄核換美不制裁 伊仍拒開放荷姆茲海峽</a></p></p><p><p><a href=\"https://newtalk.tw/news/view/2026-04-06/1028324\" target=\"_blank\">川普死了謠言瘋傳！多天未公開露面 白宮緊急闢謠：仍在白宮辦公</a></p></p><p><p><a href=\"https://newtalk.tw/news/view/2026-04-07/1028452\" target=\"_blank\">既然贏了就該收錢! 川普震撼提議 : 非伊朗 美國才該徵收核姆茲通行費</a></p></p><p><p><a href=\"https://newtalk.tw/news/view/2026-04-07/1028413\" target=\"_blank\">學川普的? 不懼最後期限 伊稱已經贏了 只接受「這一種」戰爭局面</a></p></p><p><p><a href=\"https://newtalk.tw/news/view/2026-04-07/1028397\" target=\"_blank\">走漏消息險害營救破局？川普2日未眠怒查誰洩密 傳助美飛官伊數十居民被捕</a></p></p>", "link": "https://newtalk.tw/news/view/2026-04-08/1028622", "published_my": "260408 104207", "site": "newtalk", "label": "全部"}
{"title": "YTR被爆雞雞不到8公分  她護航「已經夠用」", "summary": "〔娛樂頻道／綜合報導〕前男團Gentleman成員「Wish」朱宇謀被前女友、女星林倪安毀滅性爆料，狠撕陽光暖男假面具，勁爆的是，逾10位受害女性向林倪安吐露被Wish傷害諸多惡劣行徑，他那話兒...…", "link": "https://ent.ltn.com.tw/news/breakingnews/5396637", "published_my": "260408 104316", "site": "ltn", "label": "即時"}
{"title": "曾國城擁4房傳賣百坪別墅 開價近億元等嘸人買", "summary": "資深主持人曾國城出道超過35年，主持《天才衝衝衝》、《型男大主廚》等長壽綜藝節目，近年也將乾拌麵副業經營得有聲有色。而對房地產眼光獨到的他，據傳在台北至少擁有4間房產，總值近4億元，但近日有消息傳出他", "link": "https://www.chinatimes.com/realtimenews/20260408001604-260404", "published_my": "260408 104400", "site": "chinatimes", "label": "chinatimes"}
{"title": "檢廉搜索扣押百本存摺掀波！陳佩琪親上火線曝家人理財內幕：嚇到人嗎？", "summary": "", "link": "https://www.setn.com/News.aspx?NewsID=1819285", "published_my": "260408 104400", "site": "setn", "label": "setn"}
{"title": "峮峮爆新歡「小15歲男星接送」 2年前同台細節遭挖！互動充滿電力", "summary": "", "link": "https://www.setn.com/News.aspx?NewsID=1819372", "published_my": "260408 104400", "site": "setn", "label": "setn"}
{"title": "美伊停火兩週 白宮高喊：這是美國的勝利！", "summary": "在針對伊朗的「最後通牒」倒數之際，美國總統川普接受巴基斯坦總理夏立夫（Shehbaz Sharif）的提議，與伊朗暫時停火兩週。白宮新聞秘書李威特（Karoline Leavit...…", "link": "https://news.ltn.com.tw/news/world/breakingnews/5396620", "published_my": "260408 104415", "site": "ltn", "label": "即時"}
{"title": "水泥車翻覆釀1死！國一東湖段6車連環撞 小貨車鬼切畫面曝光", "summary": "", "link": "https://www.setn.com/News.aspx?NewsID=1819377", "published_my": "260408 104500", "site": "setn", "label": "setn"}
{"title": "桃園食安滴水不漏？ 張善政：連年稽查市集美食衛生", "summary": "桃園市長張善政8日主持市政會議，他說，近日南部發生食物中毒，民眾也擔心食安問題，他說，桃園113年發生忠貞市場越南法國麵包食安事件，市府檢視稽查制度，啟動全市「市集美食衛生查核輔導計畫」，每年持續進行", "link": "https://www.chinatimes.com/realtimenews/20260408001672-260421", "published_my": "260408 104500", "site": "chinatimes", "label": "chinatimes"}
{"title": "民眾黨延後懲處李貞秀中評會 律師嗆：不敢開除就是坐實中共指派", "summary": "<br />\n<br />\nNewtalk新聞 <br />\n<br />\n<p>民眾黨立委李貞秀因先前自爆，新竹市長高虹安拿前民眾黨主席柯文哲700萬元，遭移送中評會處置。近日更遭踢爆，李貞秀正是當年檢舉高虹安涉詐助理費證人之一。原訂民眾黨中評會將於9日開會議處，但傳出會議會延後到13日。對此律師黃帝穎今（8）日就嗆，前後任民眾黨主席不敢開除中共指派接班人李貞秀，更質疑鄭習會掩護中國人李貞秀黨紀案。</p><br />\n<p>李貞秀日前於直播中爆料，高虹安拿柯文哲700萬元，引起白營及其支持者反彈。儘管她事後道歉，但仍澆不息黨內怒火，民眾黨中評會也立案調查。除此之外，李貞秀近日更背踢爆，李貞秀正式當年檢舉高虹安涉詐助理費案證人之一，並與曾代表民眾黨參選竹縣竹北市長，爾後遭因酒駕遭開除黨籍的林冠年關係密切，讓不少民眾黨支持者不滿，紛紛要求對李貞秀開鍘。</p><br />\n<p>民眾黨中評會原定9日開會議處李貞秀之案，而李貞秀昨日受訪被問及此事時，表示尊重中評會獨立裁決。然而，傳出9日召開中評會將延至13日。對此，民眾黨中評會主委李偉華證實會議延期一事，並聲稱因為有委員出國，致使會議延期。</p><br />\n<p>黃帝穎指出，新北地院昨日就前民眾黨新住民委員會主任委員徐春鶯涉嫌違反《銀行法》及《反滲透法》等案首度開庭審理。檢方提示證據，中共官員與徐春鶯對話紀錄，揭露徐春鶯曾向對岸官員精準彙報柯文哲京華城案進度與民眾黨動態「柯文哲恐收押」、「李貞秀接立委前，民進黨一定會再炸一波」等。最嚴重的是，中共官員定調「李貞秀接班應該沒問題了吧？」</p><br />\n<p>他質疑，黃國昌和柯文哲若不敢開除李貞秀，那當然坐實接受中共指派不分區接班人，只能奉命行事。尤其黃國昌被立院國民黨團總爭傅崐萁摸頭的直播畫面歷歷在目，「鄭習會要民眾黨吞下李貞秀黨紀案？！」</p><br />\n<p>黃帝穎認為，民眾黨是否接受中共指派接班人、以及鄭習會是否要被傅崐萁摸頭的黃國昌把黨紀吞下去，觀察指標是民眾黨中評會是否拖延或停權「打假球」不敢開除李貞秀？</p><p><p>延伸閱讀：</p></p><p><p><a href=\"https://newtalk.tw/news/view/2026-04-07/1028409\" target=\"_blank\">李貞秀幹嘛不「躺平」就好？她曝：中評會開除李貞秀將引爆兩顆深水炸彈！</a></p></p><p><p><a href=\"https://newtalk.tw/news/view/2026-04-07/1028414\" target=\"_blank\">卓榮泰步上台表拒李貞秀質詢  韓國瑜：請行政院長尊重憲法質詢權</a></p></p><p><p><a href=\"https://newtalk.tw/news/view/2026-04-07/1026313\" target=\"_blank\">民意多數反對李貞秀當立委！小笠原欣幸：民眾黨讓她交棒比較明智</a></p></p><p><p><a href=\"https://newtalk.tw/news/view/2026-04-07/1028373\" target=\"_blank\">柯文哲自詡雍正帝...李貞秀自稱鈕祜祿氏 前白營高層：妳是要跟正宮陳佩琪「搶位」？</a></p></p><p><p><a href=\"https://newtalk.tw/news/view/2026-04-07/1028502\" target=\"_blank\">嘉義市長藍白合張啓楷勝出  黃國昌：高水準君子之爭 </a></p></p>", "link": "https://newtalk.tw/news/view/2026-04-08/1028621", "published_my": "260408 104524", "site": "newtalk", "label": "全部"}
{"title": "罷免布條遭撕！村長姪子氣到動手全認了 宜蘭崙埤村選戰火藥味炸裂", "summary": "宜蘭縣大同鄉崙埤村長罷免風波延燒！罷免案領銜人雅威米尚指控，3月29日傍晚其住處前懸掛的罷免布條遭人毀損，警方追查發現涉案者為現任村長吳秉宗36歲姪子吳男，吳男到案後坦承因一時氣憤動手，警方訊後已依違", "link": "https://www.chinatimes.com/realtimenews/20260408001714-260402", "published_my": "260408 104600", "site": "chinatimes", "label": "chinatimes"}
{"title": "王惠美遞件爭場館遭李洋淡回6字 林楚茵：不如打電話叫藍委放行總預算", "summary": "", "link": "https://www.setn.com/News.aspx?NewsID=1819382", "published_my": "260408 104600", "site": "setn", "label": "setn"}
{"title": "周杰倫曾到場力挺！邱凱偉澳洲珍奶店「無預警收攤」 經紀人發聲曝內情", "summary": "", "link": "https://www.setn.com/News.aspx?NewsID=1819371", "published_my": "260408 104600", "site": "setn", "label": "setn"}
{"title": "聯勇操演震撼！陸軍234旅展現強大火力", "summary": "屏東恆春半島三軍聯訓基地今日備受矚目的「聯勇操演」進入實彈射擊重頭戲！陸軍234旅聯合航特部展現精實的聯合作戰戰力。隨著反擊命令下達，各式重裝兵器輪番開火，震耳欲聾的砲聲...…", "link": "https://news.ltn.com.tw/news/def/breakingnews/5396599", "published_my": "260408 104612", "site": "ltn", "label": "即時"}
{"title": "聯結車毒駕撞死國道工程緩撞車司機 二審維持8年5月", "summary": "新竹縣某交通公司43歲林姓聯結車駕駛，去年4月8日吸食安非他命後上路，行經國道1號南向桃園楊梅路段時失控撞上工程緩撞車，造成駕駛當場死亡。桃園地院國民法官法庭依毒駕致死罪判處8...…", "link": "https://news.ltn.com.tw/news/society/breakingnews/5396632", "published_my": "260408 104613", "site": "ltn", "label": "即時"}
{"title": "毀損選舉看板挑戰公權力？ 高市前鎮警火速追人查緝到案", "summary": "<br />\n<br />\nNewtalk新聞 <br />\n<br />\n<p>高雄市警察局前鎮分局員警昨(7)日2時許在保泰路公車站牌，主動發現市議員參選人鄧巧佩選舉看板疑遭刮損，積極聯繫參選人服務處，說明現場狀況，鄧巧佩於昨天16時30分許至瑞隆派出所完成報案。前鎮分局立即成立專案小組，迅速掌握涉案對象身分及動向，鎖定特定對象，並於昨晚查緝到案。</p><br />\n<p>前鎮分局專案小組結合科技偵查手段，調閱周邊監視器影像，並透過路口監視系統進行影像比對、行蹤軌跡分析及時序比對，迅速掌握涉案對象身分及動向，經循線追查，於昨日23時許將年約49歲的涉案人顏姓男子查緝到案。據顏男供稱係等候公車時，臨時起意以隨身攜帶鑰匙刮損看板。</p><br />\n<p>全案調查後依觸犯《刑法》第354條「毀損罪」及《公職人員選舉罷免法》第 98 條「妨害他人競選罪」，移送高雄地方檢察署偵辦。前鎮分局強調，民眾如有任何問題，應循正當管道解決，切勿行使非法或非理性行為，以免觸法，警方對於任何違法行為絕對依法辦理，迅速查緝，絕不寬貸。</p><p><p>延伸閱讀：</p></p><p><p><a href=\"https://newtalk.tw/news/view/2026-04-07/1028530\" target=\"_blank\">公車站牌廣告遭惡意毀損 鄧巧佩報案：民主競爭不該跨越底線</a></p></p><p><p><a href=\"https://newtalk.tw/news/view/2026-04-07/1028515\" target=\"_blank\">正義市場潤餅疑似中毒事件 陳慧文：市府應建請雄檢執行「假扣押」</a></p></p><p><p><a href=\"https://newtalk.tw/news/view/2026-04-08/1028605\" target=\"_blank\">徐春鶯涉國安組織滲透  她喊話柯文哲說清楚：民眾黨有沒有跟孫憲、楊文濤見過面？</a></p></p><p><p><a href=\"https://newtalk.tw/news/view/2026-04-08/1028588\" target=\"_blank\">徐春鶯的「閒聊」讓人毛骨悚然！他曝：接收統戰指令  精準回報柯文哲案情</a></p></p><p><p><a href=\"https://newtalk.tw/news/view/2026-04-07/1028430\" target=\"_blank\">明討論「18歲公民權入選罷法」 青年團體籲三黨、政院延續支持</a></p></p>", "link": "https://newtalk.tw/news/view/2026-04-08/1028614", "published_my": "260408 104619", "site": "newtalk", "label": "全部"}
{"title": "伊朗、阿曼擬對荷莫茲海峽收費 停火方案「1點」疑留後門", "summary": "在中東戰火尚未完全平息之際，伊朗與阿曼傳出將對通行荷莫茲海峽的船隻收取費用，引發國際關注。同時，伊朗提出的10點停火方案也被發現中英文版本存在關鍵差異，外界質疑其中可能暗藏談判策略甚至「留後門」。美聯", "link": "https://www.chinatimes.com/realtimenews/20260408001680-260408", "published_my": "260408 104700", "site": "chinatimes", "label": "chinatimes"}
{"title": "不戰2026！林右昌赴美智庫任訪問學人 預告2028共同打拚", "summary": "民進黨前秘書長林右昌請辭後動向備受關注，也曾被點名角逐年底縣市長選戰，他今天宣布下週將前往美國華府智庫「印太安全研究所」（Institute of Indo-pacific Se...…", "link": "https://news.ltn.com.tw/news/politics/breakingnews/5396647", "published_my": "260408 104704", "site": "ltn", "label": "即時"}
{"title": "信錦轉投資工智聯科技 智慧製造展大秀核心實力", "summary": "樞紐及機構件大廠信錦企業（1582）轉投資工智聯科技積極發展智慧製造領域，協助企業實現智慧製造與淨零轉型，工智聯科技今日至10日在南港展覽館參加智慧製造展，全面展示其在智...…", "link": "https://ec.ltn.com.tw/article/breakingnews/5396636", "published_my": "260408 104717", "site": "ltn", "label": "即時"}
{"title": "澳總理歡迎美伊停火2週 呼籲持續緩和局勢", "summary": "美國總統川普7日表示，若伊朗不滿足要求，整個文明都將滅亡，但之後說已與伊朗達成為期2週的停火協議。澳洲總理艾班尼斯今（8）日稱，美國總統川普威脅摧毀伊朗民用基礎設施的言論並不恰...…", "link": "https://news.ltn.com.tw/news/world/breakingnews/5396619", "published_my": "260408 104743", "site": "ltn", "label": "即時"}
{"title": "暫別台灣！林右昌將赴美智庫任訪問學人：為民進黨2028執政打拚", "summary": "<br />\n<br />\nNewtalk新聞 <br />\n<br />\n<p>內政部前部長林右昌今（8）日表示，他將於下週出發暫時離開台灣一段時間，擔任美國華府智庫「印太安全研究所」的訪問學人。他說，希望在回來的時候，能帶回進步務實的治理能力以及全新充滿正向能量的自己，接著跟大家一起為守護台灣與民進黨在2028年的繼續執政來打拚。</p><br />\n<p>林右昌今天透過臉書發文表示，他受邀前往「印太安全研究所」（Institute of Indo-pacific Security，IIPS）擔任訪問學人，將於下週出發暫時離開台灣一段時間。他說，上半年，他將集中在華府參與相關活動並進行拜會與研究，更廣泛地結識美國友人；下半年，由於美國將在11月初舉辦期中選舉，則會前往幾個重要選舉州進行拜訪和觀選。</p><br />\n<p>林右昌指出，他從去年以來花了許多時間細心觀察當前國際政經局勢的變化，深深感到當前世界情勢與1989年東西冷戰結束時的大變局，有許多異曲同工相似之處，但當時大家知道世界將會是「一超多強」的格局。不過，他說，香港反送中運動、Covid-19、俄烏戰爭，以及區域衝突，再加上AI人工智慧的爆炸性發展等，大家對世界如何變化沒有明確的方向和把握。</p><br />\n<p>林右昌表示，這趟訪問學人之行，是經過深思熟慮的準備，並不是去「沉潛」，而是一場「鍛煉」與「修行」。他感謝賴清德總統的建議與鼓勵，分享如何利用立法院會期空檔到哈佛大學進修的心路歷程與心得。他說，賴總統切身的經驗分享給了他很大的啟發與勇氣，也讓他下定決心接受邀請與挑戰。</p><br />\n<p>林右昌也說，他也去拜訪前總統蔡英文、立法院前院長游錫堃以及多位政治前輩，對方給了他許多很有政治智慧的價值觀點，讓他的思慮更為明朗清晰，也讓他確信這個決定，不管是對他個人或是執政團隊而言，都是正確而且必要的選擇。</p><br />\n<p>林右昌表示，民進黨中央執政已經邁入連續第三個任期，但內外的挑戰也變得更加嚴峻；台灣人民雖然再次給民進黨機會，但對民進黨執政的要求與標準也同樣會變得更高。他說，民進黨今年9月建黨將屆滿40週年，應該如何思考回應下一個40年的挑戰，帶給台灣人民更大的幸福。</p><br />\n<p>林右昌指出，面對當下中國全面性的脅迫侵擾，他將鎖定研究如何從社會韌性、城市安全、非軍事防衛能力三面向，來提升民主國家的全社會防禦韌性；如何強化在地緣政治與混合威脅下的城市治理力量與安全角色；以及，如何因應AI驅動的社會變革與國家治理的挑戰。</p><br />\n<p>林右昌說，希望自己能在更大的世界裡能累積更多的能力與連結。在回來之時，能帶回進步務實的治理能力以及全新充滿正向能量的自己，接著跟大家一起為守護台灣與民進黨在2028年的繼續執政來打拚。</p><p><p>延伸閱讀：</p></p><p><p><a href=\"https://newtalk.tw/news/view/2026-04-08/1028605\" target=\"_blank\">徐春鶯涉國安組織滲透  她喊話柯文哲說清楚：民眾黨有沒有跟孫憲、楊文濤見過面？</a></p></p><p><p><a href=\"https://newtalk.tw/news/view/2026-04-08/1028615\" target=\"_blank\">美威脅「摧毀文明」不到半天決議停火兩周 伊朗稱4/10日談判 WTI重挫19%、黃金重返4,800關口</a></p></p><p><p><a href=\"https://newtalk.tw/news/view/2026-04-08/1028609\" target=\"_blank\">鄭麗文訪中傷選情？ 牛煦庭：開大門走大路才能揮別PTSD</a></p></p><p><p><a href=\"https://newtalk.tw/news/view/2026-04-07/1028420\" target=\"_blank\">訪中帶上「九二共識」創始人  鄭麗文再喊話賴清德和解 </a></p></p><p><p><a href=\"https://newtalk.tw/news/view/2026-04-07/1028539\" target=\"_blank\">賴清德談台美加強合作  美眾議員：全球自由與台灣未來緊密相關</a></p></p>", "link": "https://newtalk.tw/news/view/2026-04-08/1028623", "published_my": "260408 104751", "site": "newtalk", "label": "全部"}
{"title": "政院遲未任命4人事 中選會認了：應該會影響年底九合一選舉", "summary": "藍白日前於立院通過中選會主委被提名人游盈隆等4人的人事同意權案，但行政院不滿另外3人未過，因此尚未發文任命，將另提3人等立院通過後再一併辦理交接。藍委張智倫今（8日）質疑，政院公然行政怠惰，會不會影響", "link": "https://www.chinatimes.com/realtimenews/20260408001585-260407", "published_my": "260408 104800", "site": "chinatimes", "label": "chinatimes"}
{"title": "毒害基隆河！黑心商害10萬人喝毒水狠撈4億 32人被起訴", "summary": "基隆地檢署偵辦去年11月基隆和新北汐止10餘萬自來水用戶遭污染案，經過4個多月密集偵辦，今天（8日）偵結，將游、黃、范、顧等4家公司負責人與員工等共犯共32人，依違反廢棄物清理...…", "link": "https://news.ltn.com.tw/news/society/breakingnews/5396639", "published_my": "260408 104851", "site": "ltn", "label": "即時"}
{"title": "高雄春捲中毒案！業者「2句」嗆衛生局 受害者怒喊告", "summary": "", "link": "https://www.setn.com/News.aspx?NewsID=1819267", "published_my": "260408 104900", "site": "setn", "label": "setn"}
{"title": "白黨魁有巨變？不只掃光小菜 柯文哲被爆私下託付蔡壁如「暖身」救援", "summary": "民眾黨創黨主席柯文哲日前赴嘉義輔選，同框前立委蔡壁如，兩人同桌吃飯意外引發「掃光小菜」話題。由於柯文哲與民眾黨現任主席黃國昌目前雙雙陷入司法危機，最新消息傳出，柯文哲認為黃國昌在2026年底主席任期屆", "link": "https://www.chinatimes.com/realtimenews/20260408001655-260407", "published_my": "260408 104900", "site": "chinatimes", "label": "chinatimes"}
{"title": "英國人逛台灣超市嚇到  物價差不多「薪水卻差2倍」", "summary": "近日一名英國男子來台逛超市後，驚呼很貴，引發網友討論，《中時新聞網》進一步訪問居住在倫敦近郊的英國人，對方坦言，當地超市價格不算高，真正昂貴的是外食、房租與交通。整體來看，英國與台灣的超市價格差異不大", "link": "https://www.chinatimes.com/realtimenews/20260408001641-260405", "published_my": "260408 104900", "site": "chinatimes", "label": "chinatimes"}
{"title": "《興櫃股》普瑞博四大市場同傳喜訊 股價在平盤上下游移", "summary": "普瑞博(6847)在歐洲、東南亞、台灣與中東等四大市場同步傳出喜訊，可望迎來營收大幅成長的關鍵拐點，今(8)日股價開低後，見買單點火，股價在平盤上下游移。  普瑞博自主研發的「紅血球濃縮液用減白過濾器", "link": "https://www.chinatimes.com/realtimenews/20260408001734-260410", "published_my": "260408 104900", "site": "chinatimes", "label": "chinatimes"}
{"title": "萊爾富將開賣神級茶飲 全場嗨翻：去日本天天喝", "summary": "萊爾富今年初引進日本人氣飲品「京都檸檬水」與「消腫檸檬氣泡飲」，在社群掀起話題。最近有網友發現，萊爾富又將開賣日本知名品牌「綾鷹」的茶飲，大票民眾興奮表示，去日本玩每天都會喝；還有一名嫁來台灣的日本女", "link": "https://www.chinatimes.com/realtimenews/20260408001671-260405", "published_my": "260408 104900", "site": "chinatimes", "label": "chinatimes"}
{"title": "鄭麗文訪中「國共合滅中華民國」汪浩：向侵略者展示抵抗意志崩潰", "summary": "<br />\n<br />\nNewtalk新聞 <br />\n<br />\n<p>國民黨主席鄭麗文展開訪中行，可能將與中共總書記習近平會晤。她接受國台辦主任宋濤晚宴款待時宣稱，這次訪中再次證明，在兩岸關係上，「九二共識、反對台獨」的政治基礎「依舊歷久彌新」。對此，作家汪浩痛批：「這場『鄭習會』換不來穩定，只會讓台灣變得更不安全。一個在中共面前配合演出「一中政策」的政黨，正親手將中華民國推向歷史的終點。」</p><br />\n<p>汪浩在臉書發文寫道：「國共合作，消滅中華民國？2026年4月7日，鄭麗文率領規模空前的國民黨訪問團訪中。這場名為『和平』的旅行，實則是一場極不對稱的政治獻祭。這場交往並非互惠，而是向世界展示：台灣最大在野黨願意在中共設定的『一中框架』下順從。若無共產黨這個『主角』搭建統戰舞台，國民黨這齣『配角』戲根本無以為繼。」</p><br />\n<p>汪浩指出：「鄭麗文在慈湖向蔣中正報告『和平』，卻無視中共併吞台灣的野心從未改變。中共對台的軍事壓力，本質是為了挑戰美國霸權、建立海權，與台灣誰執政無關。國民黨天真地以為避戰能換來和平，實則是在向侵略者展示『抵抗意志的崩潰』。真正的和平建立在勢力均衡的『僵局』之上，而非單方面的政治施捨。」</p><br />\n<p>汪浩續指：「陸委會主委邱垂正的警告震聾發聵：鄭麗文此行若不當面要求中共停止軍機繞台、不嚴正捍衛中華民國存在的事實，就是落入『消滅中華民國』的敘事陷阱。當國民黨在國際上釋放台灣內部對主權存有分歧的錯誤訊號，不僅稀釋了台灣的民主韌性，更讓美方因國民黨的作爲，對台灣人保衛國家的決心產生懷疑。」</p><p><p>延伸閱讀：</p></p><p><p><a href=\"https://newtalk.tw/news/view/2026-04-07/1028345\" target=\"_blank\">鄭習會是國民黨的一場慘烈「語義撤退」汪浩：鄭麗文賣了中華民國</a></p></p><p><p><a href=\"https://newtalk.tw/news/view/2026-04-06/1028291\" target=\"_blank\">國民黨鼓吹「和平才能躺平」卻誤解中國用語！沈榮欽：實在太蠢了</a></p></p><p><p><a href=\"https://newtalk.tw/news/view/2026-04-07/1028361\" target=\"_blank\">鄭麗文訪中前夕「8艘共艦圍台」 管碧玲：讓台人在台灣之籠躺平？</a></p></p><p><p><a href=\"https://newtalk.tw/news/view/2026-04-06/1028246\" target=\"_blank\">鄭習會前夕不平靜？美媒：中國突劃40天空域釋訊號 </a></p></p><p><p><a href=\"https://newtalk.tw/news/view/2026-04-06/1028282\" target=\"_blank\">「鄭習會」在即！ 鈕則勳揭：「這一招」若發酵 反制綠營抗中有望</a></p></p>", "link": "https://newtalk.tw/news/view/2026-04-08/1028562", "published_my": "260408 105036", "site": "newtalk", "label": "全部"}
{"title": "印尼門戶變水簾洞！雅加達機場天花板崩塌 雨灌候機室如瀑布", "summary": "印尼雅加達近日遭極端氣候與連日暴雨襲擊，導致蘇加諾-哈達國際機場（Soekarno-Hatta International Airport）3號航站樓於昨日（6日）發生天花板坍塌...…", "link": "https://news.ltn.com.tw/news/world/breakingnews/5396574", "published_my": "260408 105059", "site": "ltn", "label": "即時"}
{"title": "堅持過去國民黨核心價值　黃暐瀚開撕：我怎麼變綠暐瀚了？", "summary": null, "link": "https://www.mirrormedia.mg/story/20260408edi004", "published_my": "260408 105100", "site": "mirrormedia", "label": "鏡傳媒"}
{"title": "別讓血糖偷走記憶！醫籲：控制飲食、運動、多出門聊天", "summary": "糖尿病不僅會影響心臟、腎臟、肌肉及大腦，也可能導致高齡者面臨失智問題！花蓮門諾醫院副院長、神經內科醫師王志弘表示，糖尿病與失智症盛行率隨年紀增長而增加，據研究指出，若確診糖尿病後7年內，罹患失智症的機", "link": "https://www.chinatimes.com/realtimenews/20260408001642-260418", "published_my": "260408 105100", "site": "chinatimes", "label": "chinatimes"}
{"title": "南投死亡車禍！鐵工孝子載貨途中「嵌駕駛座」慘死 老父母聞死訊心碎", "summary": "", "link": "https://www.setn.com/News.aspx?NewsID=1819387", "published_my": "260408 105100", "site": "setn", "label": "setn"}
{"title": "太受歡迎也有問題！MacBook Neo不到2萬賣翻、蘋果陷入兩難", "summary": "蘋果推出的 MacBook Neo 以不到 2 萬元的親民價格切入市場，一上市就掀起熱賣。不過，這樣的成功背後，反而讓蘋果陷入一個不小的兩難…", "link": "https://3c.ltn.com.tw/news/65610", "published_my": "260408 105112", "site": "ltn", "label": "即時"}
{"title": "MiLB》台灣隊國手同場較勁！ 鄭宗哲、「費仔」都敲三壘安打", "summary": "效力紅襪3A的台灣好手鄭宗哲、守護者3A的台灣混血強打「費仔」費爾柴德（Stuart Fairchild），同為經典賽台灣隊國手的兩人今天同場較勁。鄭宗哲擊出一支三壘安打，...…", "link": "https://sports.ltn.com.tw/news/breakingnews/5396565", "published_my": "260408 105153", "site": "ltn", "label": "即時"}
{"title": "東海空域管制長達40天　馬依翔：背後戰略意涵恐有四重目的", "summary": "<br />\n<br />\nNewtalk新聞 <br />\n<br />\n<p>鄭麗文訪中之際，外媒報導中國於東海及黃海一帶劃設多處空域保留區，管制長達40天，由於解放軍與中國民航局未公布任何說明，外界多認為此舉可能涉及空戰戰術訓練。對此，曾任職國安單位的退役上校、台灣基進秘書長馬依翔認為，此舉戰略意涵遠不止於此，背後同時服務多重目的：對日施壓、消耗美軍資源、練兵台海情境，以及在中東衝突升溫之際為中國的全球戰略布局提供掩護。</p><br />\n<p>馬依翔指出，解放軍在江蘇至浙江外海實施全高度空域管制，所演練的正是對日本海空力量的拒止能力。只要這片空域持續處於戰備管控狀態，日本自衛隊在評估介入成本時就必須將此納入計算，難以輕易南向策應美軍行動。與此同時，中國長達40天的持續管控，本質上也是對美軍印太司令部的壓力測試，讓美軍不得不維持高強度偵察與警戒，若從亞太抽調兵力支援中東，就勢必出現西太平洋的空窗與風險。馬依翔示警，若這類封鎖演變為常態，美國在西太平洋的部署將被迫從前進偵察轉向分散防禦，恐使第一島鏈局部失效。</p><br />\n<p>他分析，相較於過去「先宣布再管制」的慣例，中國這次「先卡位、不解釋」的做法一旦常態化，將使第一島鏈國家與美軍持續面臨難以定性的模糊壓力，是典型的「灰色作戰」手法。馬依翔也強調，中國此次40天管制的真正考驗，或許不在於解放軍最終是否動用這片空域，而在於美日台在模糊壓力長期累積下，集體回應機制是否仍能保持足夠的靈敏度與協調性。</p><p><p>延伸閱讀：</p></p><p><p><a href=\"https://newtalk.tw/news/view/2026-04-08/1028593\" target=\"_blank\">鄭麗文赴中同日！共機2架次逾越中線 海空兵力持續擾台 </a></p></p><p><p><a href=\"https://newtalk.tw/news/view/2026-04-08/1028594\" target=\"_blank\">中國劃5空域保留區  蔡明彥：到川習會前一週、意在測試美國 </a></p></p><p><p><a href=\"https://newtalk.tw/news/view/2026-04-07/1028519\" target=\"_blank\">美國武器還是中國友誼? 鄭麗文訪中 CNN：伊戰事牽動台灣「美中路線」辯論</a></p></p><p><p><a href=\"https://newtalk.tw/news/view/2026-04-07/1028482\" target=\"_blank\">解放軍運-9Q 現身東海巡邏 日機緊盯! 專家：大幅提升反潛能力</a></p></p><p><p><a href=\"https://newtalk.tw/news/view/2026-04-06/1028255\" target=\"_blank\">生死一線！美軍低空逃離伊朗　敵軍逼近「差一步全滅」畫面曝 </a></p></p>", "link": "https://newtalk.tw/news/view/2026-04-08/1028624", "published_my": "260408 105157", "site": "newtalk", "label": "全部"}
{"title": "MLB》就是贏不了山本！藍鳥王牌對道奇失利重演去年惡夢", "summary": "藍鳥在多倫多主場復仇失敗，道奇首戰14比2大勝之後，隔天派出王牌投手山本由伸，重演藍鳥去年的惡夢。山本由伸6局失1分（在噓聲中投到第7局），加上大谷翔平、塔克（Kyle Tucker）、威爾史密斯（W", "link": "https://www.chinatimes.com/realtimenews/20260408001703-260403", "published_my": "260408 105200", "site": "chinatimes", "label": "chinatimes"}
{"title": "美威脅「摧毀文明」不到半天決議停火兩周 伊朗稱4/10日談判 WTI重挫19%、黃金重返4,800關口", "summary": "<br />\n<br />\nNewtalk新聞 <br />\n<br />\n<p>就在美國總統川普昨（7）日放話「要讓伊朗整個文明消亡」的威脅不到 12 小時，美伊緊張局勢戲劇性反轉。川普於社群媒體宣布與伊朗同意進行為期兩周的停火，以完成結束戰爭的談判，以色列也接受提議。隨後，德黑蘭聲稱，本周五起，兩國將於巴基斯坦首都伊斯蘭瑪巴德進行談判。</p><br />\n<p>此重大消息致原油價格跳水，五月交割的西德州中質原油（WTI）期貨最低跌到 91.1 美元／桶，跌幅 19%；布蘭特原油（Brent）期貨報 91.72 美元／桶，跌幅 16%；黃金現貨價格今（8 日）早最高報 4,856 美元，現報 4,811.97 美元，漲幅 2.26%。在此之前，油價漲到每桶超過 115 美元，而金價近一個月來回檔了近 7%。</p><br />\n<figure class=\"news_img open-gallery clearfix\"><img alt=\"▲在美國與伊朗達成暫時停火協議後，市場避險情緒回穩，現貨金價一度漲逾 3%。 圖：Investing.com \" class=\"cjImg img857305\" height=\"962\" src=\"https://s.newtalk.tw/album/album/1/69d5bf8f1a6f0.png\" title=\"▲在美國與伊朗達成暫時停火協議後，市場避險情緒回穩，現貨金價一度漲逾 3%。 圖：Investing.com \" width=\"1798\" /> <figcaption class=\"mainpic clearfix\" style=\"clear: both;\">▲在美國與伊朗達成暫時停火協議後，市場避險情緒回穩，現貨金價一度漲逾 3%。 圖：Investing.com </figcaption></figure><br />\n<p>川普的貼文還寫到，基於巴基斯坦總理夏巴茲．謝里夫（Shehbaz Sharif）等人斡旋下，且伊朗政府也已同意「全面、立即且安全地」開通荷姆茲海峽的航運，他同意暫停兩周轟炸與攻擊伊朗。川普還提到，「這將有助於最終敲定一項正式停火協議」，「我們已達成並超額完成所有軍事目標」；「對伊朗建立『長期和平』及實現『中東和平』的最終協議，目前也取得實質性進展。」</p><br />\n<p>伊朗最高國家安全委員會今日凌晨也發表聲明，根據最高領袖的建議和最高國家安全委員會批准，接受巴基斯坦提出的停火提案。據伊朗媒體引述最高國家安全委員會聲明，該國與美國的談判將於 4 月 10 日在巴基斯坦首都伊斯蘭瑪巴德展開，為期兩周。</p><br />\n<p>川普稱，美方收到德黑蘭提出的一份提案，包含 10 點內容，並認為「該提案為雙方談判提供了一個可行的基礎」；伊朗官媒則稱，談判目的是要敲定細節，目標最多在 15 天內，透過政治手段確認伊朗在戰場上取得成果，若伊美雙方同意，談判期可延長，並稱美國「被迫接受」伊方的十點提議。</p><br />\n<p>伊朗官媒稱，伊方 10 點提議包含在能協調的情況下，讓伊朗武裝部隊控制荷姆茲海峽通行權、結束針對伊朗及其盟友組織的戰爭、美國作戰部隊從所有海灣地區基地撤出、取消所有對伊朗的一級和二級制裁、向伊朗支付全額賠償金，及釋放所有被凍結的伊朗資產。並表示，與美國對話並不意味著結束戰爭。唯有在細節依照上述 10 點計畫最終定案後，才會接受戰爭終結。</p><br />\n<p>彭博市場策略師 Mark Cranfield 表示，股票、石油、債券和美元的初步波動表明，投資人傾向於押注最壞情況將得以避免。但他同時強調，「在可信的退出路徑出現前，還有很長的路要走，即便如此，油價可能在未來幾個月內仍將帶有內嵌的戰爭溢價」；Westpac Banking Corp 大宗商品研究主管 Robert Rennie 認為，「物理系統無法迅速恢復原狀，重啟關停油井、重新調配人員和船隻、重建煉廠庫存，都需要數月時間。」</p><br />\n&nbsp;<p>※Newtalk提醒您：<br />#投資一定有風險，投資有賺有賠，投資前應檢視自身能力，申購前應詳閱公開說明書。</p><p><p>延伸閱讀：</p></p><p><p><a href=\"https://newtalk.tw/news/view/2026-04-07/1028568\" target=\"_blank\">再嗆伊朗「整個文明可能將在今晚徹底滅亡！」川普：永遠無法復原</a></p></p><p><p><a href=\"https://newtalk.tw/news/view/2026-04-06/1028219\" target=\"_blank\">伊朗年初血腥鎮壓濫殺平民！川普：美國之後曾向抗議者送大量槍支</a></p></p><p><p><a href=\"https://newtalk.tw/news/view/2026-04-08/1028575\" target=\"_blank\">對伊朗通牒最後一刻 川普宣布「在開放荷姆茲海峽前提下」停火2週</a></p></p><p><p><a href=\"https://newtalk.tw/news/view/2026-04-07/1028355\" target=\"_blank\">市場聚焦美伊戰爭進展! 美股四大指數全收漲、台積電ADR漲0.80％</a></p></p><p><p><a href=\"https://newtalk.tw/news/view/2026-04-08/1028579\" target=\"_blank\">伊朗宣稱取得重大勝利「迫使」美接受10點方案! 要求撤軍解除制裁</a></p></p>", "link": "https://newtalk.tw/news/view/2026-04-08/1028615", "published_my": "260408 105205", "site": "newtalk", "label": "全部"}
{"title": "「石油美元」50年體系被鬆動？外媒揭 : 「這國」轉向是關鍵轉折點", "summary": "〔財經頻道／綜合報導〕美國和以色列對伊朗的戰爭凸顯了「石油美元」的強勢，石油美元是美國在全球貿易中佔據主導地位的基石，但經濟學家卻警告，這種貨幣體系多年來一直在逐漸瓦解。外媒指出，2年前沙烏地阿...…", "link": "https://ec.ltn.com.tw/article/breakingnews/5396464", "published_my": "260408 105217", "site": "ltn", "label": "即時"}
{"title": "提前布局卡位！中環等19檔發放股東紀念品機率高 今為最後上車日", "summary": "〔財經頻道／綜合報導〕股東會旺季報到，紀念品話題再度升溫！不少尚未公布內容的公司，吸引投資人提前卡位。\n\n\n今（8日）為19檔近5年皆有發放紀念品紀錄個股的最後買進日，包括中環（2323）、益登...…", "link": "https://ec.ltn.com.tw/article/breakingnews/5396650", "published_my": "260408 105236", "site": "ltn", "label": "即時"}
{"title": "不耐老婦呼喚竟在醫院動手打人 越南籍看護還嚷「不幹了」", "summary": "越南籍阮姓看護受雇照護罹患帕金森氏症、幾無自理能力的徐姓老婦，疑因不耐老婦頻繁呼喚，阮女竟趁家屬暫離病房之際，狠心掌摑老婦右臉，打完人還向家屬嚷嚷著要離職，徐婦趁機呼救「我被打」，家屬得知後氣炸報警提", "link": "https://www.chinatimes.com/realtimenews/20260408001730-260402", "published_my": "260408 105300", "site": "chinatimes", "label": "chinatimes"}
{"title": "日職》徐若熙挑戰8年來首見連勝 軟銀上一人是前兄弟洋投米蘭達", "summary": "效力軟銀鷹的徐若熙在今天下午5點將於福岡巨蛋進行本季第2場先發，也是首場主場先發，除了他有望對決同樣來自台灣的西武打者林安可，還有望挑戰軟銀暌違8年的洋投初登板起2連勝，...…", "link": "https://sports.ltn.com.tw/news/breakingnews/5396649", "published_my": "260408 105317", "site": "ltn", "label": "即時"}
{"title": "台灣成關鍵推手！解密全球貿易創紀錄背後內幕", "summary": "〔財經頻道／綜合報導〕全球貿易在2025年突破35兆美元（約新台幣1112兆元），但其中3分之1的成長來自人工智慧（AI），並主要集中台灣、南韓等國家。\n\n\n根據聯合國貿易和發展（UNCTAD）...…", "link": "https://ec.ltn.com.tw/article/breakingnews/5396519", "published_my": "260408 105400", "site": "ltn", "label": "即時"}
{"title": "NBA》小波爾36分但末節0分  布朗、塔圖姆率綠衫軍逆轉黃蜂收4連勝", "summary": "塞爾提克今在主場迎戰黃蜂，布朗（Jaylen Brown）攻下35分、塔圖姆（Jayson Tatum）進帳23分，聯手以113：102逆轉黃蜂，收下4連勝。\n\n\n兩隊本...…", "link": "https://sports.ltn.com.tw/news/breakingnews/5396656", "published_my": "260408 105423", "site": "ltn", "label": "即時"}
{"title": "都是汽油味！汙染自來水獲利逾4億元 基檢起訴將臣公司等32嫌", "summary": "去（2025）年11月，基隆市各地傳出自來水有汽油味，包括基隆及新北市汐止有多達15至18萬戶民眾受到影響。基隆地檢署成立專案小組展開調查，循線破獲了非法處理廢油的產業鏈，涉案4家公司不法所得高達新台", "link": "https://www.chinatimes.com/realtimenews/20260408001755-260402", "published_my": "260408 105500", "site": "chinatimes", "label": "chinatimes"}
{"title": "嘉義市藍白合民眾黨出線 侯友宜籲提共同政策、照顧人民所需", "summary": "嘉義市的藍白整合民調結果出爐，確定由民眾黨張啟楷出線，外界認為可能會對其他外縣市產生「外溢效應」。新北市長侯友宜今天表示，藍白合作在新北、宜蘭等縣市都有討論空間，最重要的是大家...…", "link": "https://news.ltn.com.tw/news/politics/breakingnews/5396648", "published_my": "260408 105534", "site": "ltn", "label": "即時"}
{"title": "作家重批鄭麗文女版吳三桂：若讓她得逞，台灣真的「躺平」", "summary": "", "link": "https://www.setn.com/News.aspx?NewsID=1819391", "published_my": "260408 105600", "site": "setn", "label": "setn"}
{"title": "鄭麗文訪中預計會習近平 李敖兒酸：草包會談！", "summary": "<br />\n<br />\nNewtalk新聞 <br />\n<br />\n<p>受中共中央總書記習近平之邀，國民黨主席鄭麗文於昨（7）日至12日率團到江蘇、上海、北京參觀訪問，而盛傳中的「鄭習會」可能將在此期間登場。與此同時，鄭麗文出發當時，正是為爭取「百分之百言論自由」鄭南榕先生自焚殉道之日。對此，李敖之子李戡就酸，所謂的鄭習會，就是「草包會談」！</p><br />\n<p>鄭麗文昨日行前記者會表示，此行前往中國訪問，就是要讓國民黨給全世界看到，不是台灣單方面的期待和平，而是讓大家相信，想透過對話交流，可化解所有歧見的誠意和決心。</p><br />\n<p>而隨鄭麗文訪中之成員包括國民黨副主席蕭旭岑、張榮恭、李乾龍、國民黨智庫副董事長李鴻源、國民黨中評會主席蘇起、袁健生、國民黨主席特別顧問李德維、國民黨文化傳播委員會主委 尹乃菁、國民黨大陸事務部主任張雅屏、國民黨青年事務發展委員會主委連勝武、國民黨發言人江怡臻、國民黨國際事務部主任董佳瑜及國民黨中央黨務顧問雷宏毅。</p><br />\n<p>而鄭麗文出發之日，正是鄭南榕殉道之日，同時也是「言論自由日」，同日國史館也舉辦的《戰後台灣政治案件：鄭南榕案史料彙編》新書發表暨座談會。李戡也出席新書座談會，並與鄭南榕女兒鄭竹梅合影。對於可能出現之鄭習會，李戡7日晚間在臉書發文表示，「與其關心草包會談，不如緬懷才子風骨」。</p><p><p>延伸閱讀：</p></p><p><p><a href=\"https://newtalk.tw/news/view/2026-04-07/1028516\" target=\"_blank\">鄭南榕逝世週年撞期「鄭習會」  吳欣岱批：國民黨躺平放棄治療</a></p></p><p><p><a href=\"https://newtalk.tw/news/view/2026-04-07/1028389\" target=\"_blank\">鄭麗文訪中前夕丟「躺平」廣告　范雲轟：1949不躺  現在叫台灣躺？</a></p></p><p><p><a href=\"https://newtalk.tw/news/view/2026-04-07/1028407\" target=\"_blank\">再喊話賴清德見面 鄭麗文：沒有「賴鄭會」很難有「賴習會」 </a></p></p><p><p><a href=\"https://newtalk.tw/news/view/2026-04-06/1028244\" target=\"_blank\">習鄭會倒數！ 林楚茵示警：防中國對外誤導「台灣可被代言」  </a></p></p><p><p><a href=\"https://newtalk.tw/news/view/2026-04-07/1028366\" target=\"_blank\">鄭麗文將訪中！陸委會點名「習政權」圖謀未變 警告勿淪統戰工具 </a></p></p>", "link": "https://newtalk.tw/news/view/2026-04-08/1028607", "published_my": "260408 105652", "site": "newtalk", "label": "全部"}
{"title": "高雄新建案…裝潢天花板「整排坍塌」畫面曝！保全逃死吐1句", "summary": "", "link": "https://www.setn.com/News.aspx?NewsID=1819341", "published_my": "260408 105700", "site": "setn", "label": "setn"}
{"title": "任職3年台積電技術員！29歲女因1事想逃離：下山能去哪？內行揭殘酷真相", "summary": "", "link": "https://www.setn.com/News.aspx?NewsID=1819388", "published_my": "260408 105700", "site": "setn", "label": "setn"}
{"title": "鄭麗文「和平之旅」 民進黨：是中華民國的催命符", "summary": "國民黨主席鄭麗文「和平之旅」出發前釋出「躺平」影片。民進黨中國部嚴正指出，歷史與現實已反覆證明，對威權「躺平」，換不來和平，只會換來更深層的控制與更大的羞辱。國民黨以「和平之旅」之名，行削弱國防、配合", "link": "https://www.chinatimes.com/realtimenews/20260408001653-260407", "published_my": "260408 105700", "site": "chinatimes", "label": "chinatimes"}
{"title": "美伊停火激勵！台股飆千點、新台幣強升破31.8元關卡", "summary": "美國與伊朗歷經多輪談判後，終於達成共識，美國總統川普宣布雙方將停火兩週，並由德黑蘭方面暫時恢復荷莫茲海峽通航。中東地緣政治風險降溫，激勵亞洲股匯市全面大漲，台股狂飆逾千點...…", "link": "https://ec.ltn.com.tw/article/breakingnews/5396660", "published_my": "260408 105758", "site": "ltn", "label": "財經"}
{"title": "峮峮爆熱戀21歲男團成員！他「自由進出香閨」全被拍 洩真實關係", "summary": "", "link": "https://www.setn.com/News.aspx?NewsID=1819389", "published_my": "260408 105900", "site": "setn", "label": "setn"}
{"title": "部醫資訊系統採購遭質疑 石崇良：依法辦理無不法", "summary": "針對外界質疑衛福部所屬醫院醫療資訊系統（HIS）採購案涉不法情事，衛福部長石崇良今（8）日強調，相關採購均依政府採購法公開辦理，程序透明，絕無不法，已要求全面清查，對於不實指控不...…", "link": "https://news.ltn.com.tw/news/life/breakingnews/5396657", "published_my": "260408 105901", "site": "ltn", "label": "生活"}
{"title": "不想砸錢養車！專家勸8款「燒錢黑洞」二手車不要買", "summary": "〔財經頻道／綜合報導〕在尋找可靠且價格合理的車輛時，許多人會選擇二手車，不過，專家表示，有些二手車存在變速箱有問題、做工品質存疑或維修、貶值等高風險，若不想買來修，福特Escape、BMW X5...…", "link": "https://ec.ltn.com.tw/article/breakingnews/5396515", "published_my": "260408 105903", "site": "ltn", "label": "財經"}
{"title": "焦點股》日月光：建廠買廠雙擴產利多  股價強彈", "summary": "日月光投控（3711）因應AI對先進封裝產能供不應求，朝自建廠與買既有廠房改雙軌並進，預計本周五（10日）將舉行高雄仁武產業園區擴產動土典禮，同時，業界也傳出洽購群創（3...…", "link": "https://ec.ltn.com.tw/article/breakingnews/5396662", "published_my": "260408 105942", "site": "ltn", "label": "財經"}